Workbook
Name _r: !#REF!
Name asd: !#REF!
Name Forecast: !#REF!
Name Step_1: !#REF!
Name Step_2: !#REF!
Name Step_3: !#REF!
Name Step_4: !#REF!
Name Step_5: !#REF!
Name Step_6: !#REF!
Name Step1: !#REF!
Name Step2: !#REF!
Name Step3: !#REF!
Name Step4: !#REF!
Name Step5: !#REF!
Name Step6: !#REF!

Sheet hist_inc_stmt
A1: Income Statement
A2: For the Fiscal Period Ending | B2: Reclassified 12 months Sep-30-2020 | C2: Reclassified 12 months Sep-30-2021 | D2: Reclassified 12 months Sep-30-2022 | E2: 12 months Sep-30-2023 | F2: 12 months Sep-30-2024
A3: Currency | B3: USD | C3: USD | D3: USD | E3: USD | F3: USD
A5: Revenue
A6: Other Revenue
A7: Total Revenue
A9: Cost Of Goods Sold
A10: Gross Profit
A12: Selling General & Admin Exp.
A13: R & D Exp.
A14: Depreciation & Amort.
A15: Amort. of Goodwill and Intangibles
A16: Other Operating Expense/(Income)
A18: Other Operating Exp., Total
A20: Operating Income
... A97: Note: For multiple class companies, per share items are primary class equivalent, and for foreign companies listed as primary ADRs, per share items are ADR-equivalent.

Sheet hist_bal_sht
A1: Balance Sheet
A2: Balance Sheet as of: | B2: Restated Sep-30-2020 | C2: Reclassified Sep-30-2021 | D2: Reclassified Sep-30-2022 | E2: Reclassified Sep-30-2023 | F2: 45565
A3: Currency | B3: USD | C3: USD | D3: USD | E3: USD | F3: USD
A4: ASSETS
A5: Cash And Equivalents
A6: Total Cash & ST Investments
A8: Accounts Receivable
A9: Total Receivables
A11: Other Current Assets
A12: Total Current Assets
A14: Gross Property, Plant & Equipment
A15: Accumulated Depreciation
A16: Net Property, Plant & Equipment
A18: Long-term Investments
A19: Goodwill
... A74: Note: For multiple class companies, total share counts are primary class equivalent, and for foreign companies listed as primary ADRs, total share counts are ADR-equivalent.

Sheet hist_scf
A1: Cash Flow
A2: For the Fiscal Period Ending | B2: Restated 12 months Sep-30-2020 | C2: 12 months Sep-30-2021 | D2: 12 months Sep-30-2022 | E2: Restated 12 months Sep-30-2023 | F2: 12 months Sep-30-2024
A3: Currency | B3: USD | C3: USD | D3: USD | E3: USD | F3: USD
A5: Net Income
A6: Depreciation & Amort.
A7: Amort. of Goodwill and Intangibles
A8: Depreciation & Amort., Total
A10: Other Amortization
A11: (Gain) Loss On Sale Of Invest.
A12: Asset Writedown & Restructuring Costs
A13: (Income) Loss on Equity Invest.
A14: Stock-Based Compensation
A15: Other Operating Activities
A16: Change in Acc. Receivable
A17: Change in Acc. Payable
... A59: Calculation Type

Sheet fin_model
B1: Financial Model ($ millions)
B3: Company name
B4: Ticker
B5: Share price as of valuation date
B6: Valuation date
B7: Most recent fiscal year-end date
B10: Income Statement | D10: =E10-1 -> 2020 | E10: =F10-1 -> 2021 | F10: =G10-1 -> 2022 | G10: =H10-1 -> 2023 | H10: =2024 -> 2024 | I10: =H10+1 -> 2025 | J10: =I10+1 -> 2026 | K10: =J10+1 -> 2027 | L10: =K10+1 -> 2028 | M10: =L10+1 -> 2029 | N10: =M10+1 -> 2030
B11: Revenue | D11: =hist_inc_stmt!B7 -> 0 | E11: =hist_inc_stmt!C7 -> 0 | F11: =hist_inc_stmt!D7 -> 0 | G11: =hist_inc_stmt!E7 -> 0 | H11: =hist_inc_stmt!F7 -> 0 | I11: =I99 -> #DIV/0! | J11: =J99 -> #DIV/0! | K11: =K99 -> #DIV/0! | L11: =L99 -> #DIV/0! | M11: =M99 -> #DIV/0! | N11: =N99 -> #DIV/0!
B12: Cost of goods sold (COGS) | D12: =-hist_inc_stmt!B9 -> 0 | E12: =-hist_inc_stmt!C9 -> 0 | F12: =-hist_inc_stmt!D9 -> 0 | G12: =-hist_inc_stmt!E9 -> 0 | H12: =-hist_inc_stmt!F9 -> 0 | I12: =I104 -> #DIV/0! | J12: =J104 -> #DIV/0! | K12: =K104 -> #DIV/0! | L12: =L104 -> #DIV/0! | M12: =M104 -> #DIV/0! | N12: =N104 -> #DIV/0!
B13: Gross Profit | D13: =SUM(D11:D12) -> 0 | E13: =SUM(E11:E12) -> 0 | F13: =SUM(F11:F12) -> 0 | G13: =SUM(G11:G12) -> 0 | H13: =SUM(H11:H12) -> 0 | I13: =SUM(I11:I12) -> #DIV/0! | J13: =SUM(J11:J12) -> #DIV/0! | K13: =SUM(K11:K12) -> #DIV/0! | ... N13: =SUM(N11:N12) -> #DIV/0!
B14: SG&A and other indirect expenses | D14: =-hist_inc_stmt!B18 -> 0 | E14: =-hist_inc_stmt!C18 -> 0 | F14: =-hist_inc_stmt!D18 -> 0 | G14: =-hist_inc_stmt!E18 -> 0 | H14: =-hist_inc_stmt!F18 -> 0 | I14: =I111 -> #DIV/0! | J14: =J111 -> #DIV/0! | K14: =K111 -> #DIV/0! | L14: =L111 -> #DIV/0! | M14: =M111 -> #DIV/0! | N14: =N111 -> #DIV/0!
B15: Operating Profit | D15: =(D13+D14) -> 0 | E15: =(E13+E14) -> 0 | F15: =(F13+F14) -> 0 | G15: =(G13+G14) -> 0 | H15: =(H13+H14) -> 0 | I15: =(I13+I14) -> #DIV/0! | J15: =(J13+J14) -> #DIV/0! | K15: =(K13+K14) -> #DIV/0! | ... N15: =(N13+N14) -> #DIV/0!
B16: Interest expense | D16: =hist_inc_stmt!B22 -> 0 | E16: =hist_inc_stmt!C22 -> 0 | F16: =hist_inc_stmt!D22 -> 0 | G16: =hist_inc_stmt!E22 -> 0 | H16: =hist_inc_stmt!F22 -> 0 | I16: =I118 -> #DIV/0! | J16: =J118 -> #DIV/0! | K16: =K118 -> #DIV/0! | L16: =L118 -> #DIV/0! | M16: =M118 -> #DIV/0! | N16: =N118 -> #DIV/0!
B17: Other non-operating income (expense) except interest expense & unusual | D17: =SUM(hist_inc_stmt!B26:B28)+hist_inc_stmt!B23 -> 0 | E17: =SUM(hist_inc_stmt!C26:C28)+hist_inc_stmt!C23 -> 0 | F17: =SUM(hist_inc_stmt!D26:D28)+hist_inc_stmt!D23 -> 0 | G17: =SUM(hist_inc_stmt!E26:E28)+hist_inc_stmt!E23 -> 0 | H17: =SUM(hist_inc_stmt!F26:F28)+hist_inc_stmt!F23 -> 0 | I17: =I123 -> #DIV/0! | J17: =J123 -> #DIV/0! | K17: =K123 -> #DIV/0! | L17: =L123 -> #DIV/0! | M17: =M123 -> #DIV/0! | N17: =N123 -> #DIV/0!
B18: Unusual items | D18: =SUM(hist_inc_stmt!B31:B35) -> 0 | E18: =SUM(hist_inc_stmt!C31:C35) -> 0 | F18: =SUM(hist_inc_stmt!D31:D35) -> 0 | G18: =SUM(hist_inc_stmt!E31:E35) -> 0 | H18: =SUM(hist_inc_stmt!F31:F35) -> 0 | I18: =I129 -> #DIV/0! | J18: =J129 -> #DIV/0! | K18: =K129 -> #DIV/0! | L18: =L129 -> #DIV/0! | M18: =M129 -> #DIV/0! | N18: =N129 -> #DIV/0!
B19: Earnings Before Tax | D19: =SUM(D15:D18) -> 0 | E19: =SUM(E15:E18) -> 0 | F19: =SUM(F15:F18) -> 0 | G19: =SUM(G15:G18) -> 0 | H19: =SUM(H15:H18) -> 0 | I19: =SUM(I15:I18) -> #DIV/0! | J19: =SUM(J15:J18) -> #DIV/0! | K19: =SUM(K15:K18) -> #DIV/0! | ... N19: =SUM(N15:N18) -> #DIV/0!
B20: Taxes | D20: =-hist_inc_stmt!B38 -> 0 | E20: =-hist_inc_stmt!C38 -> 0 | F20: =-hist_inc_stmt!D38 -> 0 | G20: =-hist_inc_stmt!E38 -> 0 | H20: =-hist_inc_stmt!F38 -> 0 | I20: =I133 -> #DIV/0! | J20: =J133 -> #DIV/0! | K20: =K133 -> #DIV/0! | L20: =L133 -> #DIV/0! | M20: =M133 -> #DIV/0! | N20: =N133 -> #DIV/0!
B21: Net income from continuing operations | D21: =SUM(D19:D20) -> 0 | E21: =SUM(E19:E20) -> 0 | F21: =SUM(F19:F20) -> 0 | G21: =SUM(G19:G20) -> 0 | H21: =SUM(H19:H20) -> 0 | I21: =I19+I20 -> #DIV/0! | J21: =J19+J20 -> #DIV/0! | K21: =K19+K20 -> #DIV/0! | L21: =L19+L20 -> #DIV/0! | M21: =M19+M20 -> #DIV/0! | N21: =N19+N20 -> #DIV/0!
B22: Other considerations (discontinued, noncontrolling, preferred dividends, etc.) | D22: =hist_inc_stmt!B45 -> 0 | E22: =hist_inc_stmt!C45 -> 0 | F22: =hist_inc_stmt!D45 -> 0 | G22: =hist_inc_stmt!E45 -> 0 | H22: =hist_inc_stmt!F45 -> 0 | I22: =I139 -> #DIV/0! | J22: =J139 -> #DIV/0! | K22: =K139 -> #DIV/0! | L22: =L139 -> #DIV/0! | M22: =M139 -> #DIV/0! | N22: =N139 -> #DIV/0!
B23: Net income | D23: =SUM(D21:D22) -> 0 | E23: =SUM(E21:E22) -> 0 | F23: =SUM(F21:F22) -> 0 | G23: =SUM(G21:G22) -> 0 | H23: =SUM(H21:H22) -> 0 | I23: =SUM(I21:I22) -> #DIV/0! | J23: =SUM(J21:J22) -> #DIV/0! | K23: =SUM(K21:K22) -> #DIV/0! | ... N23: =SUM(N21:N22) -> #DIV/0!
B26: Balance Sheet | D26: =D10 -> 2020 | E26: =E10 -> 2021 | F26: =F10 -> 2022 | G26: =G10 -> 2023 | H26: =H10 -> 2024 | I26: =H26+1 -> 2025 | J26: =I26+1 -> 2026 | K26: =J26+1 -> 2027 | L26: =K26+1 -> 2028 | M26: =L26+1 -> 2029 | N26: =M26+1 -> 2030
B27: Assets
B28: Cash & equivalents | D28: =hist_bal_sht!B5 -> 0 | E28: =hist_bal_sht!C5 -> 0 | F28: =hist_bal_sht!D5 -> 0 | G28: =hist_bal_sht!E5 -> 0 | H28: =hist_bal_sht!F5 -> 0 | I28: =I290 -> #DIV/0! | J28: =J290 -> #DIV/0! | K28: =K290 -> #DIV/0! | L28: =L290 -> #DIV/0! | M28: =M290 -> #DIV/0! | N28: =N290 -> #DIV/0!
B29: Other nonoperating current assets | D29: =hist_bal_sht!B11 -> 0 | E29: =hist_bal_sht!C11 -> 0 | F29: =hist_bal_sht!D11 -> 0 | G29: =hist_bal_sht!E11 -> 0 | H29: =hist_bal_sht!F11 -> 0 | I29: =I147 -> #DIV/0! | J29: =J147 -> #DIV/0! | K29: =K147 -> #DIV/0! | L29: =L147 -> #DIV/0! | M29: =M147 -> #DIV/0! | N29: =N147 -> #DIV/0!
B30: Accounts receivable | D30: =hist_bal_sht!B8 -> 0 | E30: =hist_bal_sht!C8 -> 0 | F30: =hist_bal_sht!D8 -> 0 | G30: =hist_bal_sht!E8 -> 0 | H30: =hist_bal_sht!F8 -> 0 | I30: =I152 -> #DIV/0! | J30: =J152 -> #DIV/0! | K30: =K152 -> #DIV/0! | L30: =L152 -> #DIV/0! | M30: =M152 -> #DIV/0! | N30: =N152 -> #DIV/0!
B31: Inventory | D31: 0 | E31: 0 | F31: 0 | G31: 0 | H31: 0 | I31: =I157 -> 0 | J31: =J157 -> #DIV/0! | K31: =K157 -> #DIV/0! | L31: =L157 -> #DIV/0! | M31: =M157 -> #DIV/0! | N31: =N157 -> #DIV/0!
B32: Other operating current assets | D32: 0 | E32: 0 | F32: 0 | G32: 0 | H32: 0 | I32: =I163 -> #DIV/0! | J32: =J163 -> #DIV/0! | K32: =K163 -> #DIV/0! | L32: =L163 -> #DIV/0! | M32: =M163 -> #DIV/0! | N32: =N163 -> #DIV/0!
B33: Current Assets | D33: =SUM(D28:D32) -> 0 | E33: =SUM(E28:E32) -> 0 | F33: =SUM(F28:F32) -> 0 | G33: =SUM(G28:G32) -> 0 | H33: =SUM(H28:H32) -> 0 | I33: =SUM(I28:I32) -> #DIV/0! | J33: =SUM(J28:J32) -> #DIV/0! | K33: =SUM(K28:K32) -> #DIV/0! | ... N33: =SUM(N28:N32) -> #DIV/0!
B34: PP&E | D34: =hist_bal_sht!B16 -> 0 | E34: =hist_bal_sht!C16 -> 0 | F34: =hist_bal_sht!D16 -> 0 | G34: =hist_bal_sht!E16 -> 0 | H34: =hist_bal_sht!F16 -> 0 | I34: =I169 -> #DIV/0! | J34: =J169 -> #DIV/0! | K34: =K169 -> #DIV/0! | L34: =L169 -> #DIV/0! | M34: =M169 -> #DIV/0! | N34: =N169 -> #DIV/0!
B35: Other long-term assets | D35: =hist_bal_sht!B23-hist_bal_sht!B16-hist_bal_sht!B12 -> 0 | E35: =hist_bal_sht!C23-hist_bal_sht!C16-hist_bal_sht!C12 -> 0 | F35: =hist_bal_sht!D23-hist_bal_sht!D16-hist_bal_sht!D12 -> 0 | G35: =hist_bal_sht!E23-hist_bal_sht!E16-hist_bal_sht!E12 -> 0 | H35: =hist_bal_sht!F23-hist_bal_sht!F16-hist_bal_sht!F12 -> 0 | I35: =I180 -> #DIV/0! | J35: =J180 -> #DIV/0! | K35: =K180 -> #DIV/0! | L35: =L180 -> #DIV/0! | M35: =M180 -> #DIV/0! | N35: =N180 -> #DIV/0!
B36: Long-term Assets | D36: =SUM(D34:D35) -> 0 | E36: =SUM(E34:E35) -> 0 | F36: =SUM(F34:F35) -> 0 | G36: =SUM(G34:G35) -> 0 | H36: =SUM(H34:H35) -> 0 | I36: =SUM(I34:I35) -> #DIV/0! | J36: =SUM(J34:J35) -> #DIV/0! | K36: =SUM(K34:K35) -> #DIV/0! | ... N36: =SUM(N34:N35) -> #DIV/0!
B37: Total Assets | D37: =D33+D36 -> 0 | E37: =E33+E36 -> 0 | F37: =F33+F36 -> 0 | G37: =G33+G36 -> 0 | H37: =H33+H36 -> 0 | I37: =I33+I36 -> #DIV/0! | J37: =J33+J36 -> #DIV/0! | K37: =K33+K36 -> #DIV/0! | ... N37: =N33+N36 -> #DIV/0!
B39: Liabilities
B40: Accounts payable | D40: =hist_bal_sht!B26 -> 0 | E40: =hist_bal_sht!C26 -> 0 | F40: =hist_bal_sht!D26 -> 0 | G40: =hist_bal_sht!E26 -> 0 | H40: =hist_bal_sht!F26 -> 0 | I40: =I188 -> #DIV/0! | J40: =J188 -> #DIV/0! | K40: =K188 -> #DIV/0! | L40: =L188 -> #DIV/0! | M40: =M188 -> #DIV/0! | N40: =N188 -> #DIV/0!
B41: Short-term debt | D41: 0 | E41: 0 | F41: 0 | G41: 0 | H41: 0 | I41: =I193 -> 0 | J41: =J193 -> 0 | K41: =K193 -> 0 | L41: =L193 -> 0 | M41: =M193 -> 0 | N41: =N193 -> 0
B42: Current portion of long-term debt | D42: =IF(hist_bal_sht!B28 = "-","0",hist_bal_sht!B28) -> 0 | E42: =IF(hist_bal_sht!C28 = "-","0",hist_bal_sht!C28) -> 0 | F42: =IF(hist_bal_sht!D28 = "-","0",hist_bal_sht!D28) -> 0 | G42: =IF(hist_bal_sht!E28 = "-","0",hist_bal_sht!E28) -> 0 | H42: =IF(hist_bal_sht!F28 = "-","0",hist_bal_sht!F28) -> 0 | I42: =I197 -> 400 | J42: =J197 -> 469.5 | K42: =K197 -> 0 | L42: =L197 -> 0 | M42: =M197 -> 0 | N42: =N197 -> 847.5
B43: Other current liabilities | D43: =hist_bal_sht!B32-hist_bal_sht!B26 -> 0 | E43: =hist_bal_sht!C32-hist_bal_sht!C26 -> 0 | F43: =hist_bal_sht!D32-hist_bal_sht!D26 -> 0 | G43: =hist_bal_sht!E32-hist_bal_sht!E26 -> 0 | H43: =hist_bal_sht!F32-hist_bal_sht!F26 -> 0 | I43: =I203 -> #DIV/0! | J43: =J203 -> #DIV/0! | K43: =K203 -> #DIV/0! | L43: =L203 -> #DIV/0! | M43: =M203 -> #DIV/0! | N43: =N203 -> #DIV/0!
B44: Current Liabilities | D44: =SUM(D40:D43)-D42 -> 0 | E44: =SUM(E40:E43)-E42 -> 0 | F44: =SUM(F40:F43)-F42 -> 0 | G44: =SUM(G40:G43)-G42 -> 0 | H44: =SUM(H40:H43)-H42 -> 0 | I44: =SUM(I40:I43) -> #DIV/0! | J44: =SUM(J40:J43) -> #DIV/0! | K44: =SUM(K40:K43) -> #DIV/0! | L44: =SUM(L40:L43) -> #DIV/0! | M44: =SUM(M40:M43) -> #DIV/0! | N44: =SUM(N40:N43) -> #DIV/0!
B45: Long-term debt | D45: =hist_bal_sht!B34 -> 0 | E45: =hist_bal_sht!C34 -> 0 | F45: =hist_bal_sht!D34 -> 0 | G45: =hist_bal_sht!E34 -> 0 | H45: =hist_bal_sht!F34 -> 0 | I45: =I210 -> #DIV/0! | J45: =J210 -> #DIV/0! | K45: =K210 -> #DIV/0! | L45: =L210 -> #DIV/0! | M45: =M210 -> #DIV/0! | N45: =N210 -> #DIV/0!
B46: Other long-term liabilities | D46: =SUM(hist_bal_sht!B35:B37) -> 0 | E46: =SUM(hist_bal_sht!C35:C37) -> 0 | F46: =SUM(hist_bal_sht!D35:D37) -> 0 | G46: =SUM(hist_bal_sht!E35:E37) -> 0 | H46: =SUM(hist_bal_sht!F35:F37) -> 0 | I46: =I224 -> #DIV/0! | J46: =J224 -> #DIV/0! | K46: =K224 -> #DIV/0! | L46: =L224 -> #DIV/0! | M46: =M224 -> #DIV/0! | N46: =N224 -> #DIV/0!
B47: Long-term liabilities | D47: =SUM(D45:D46) -> 0 | E47: =SUM(E45:E46) -> 0 | F47: =SUM(F45:F46) -> 0 | G47: =SUM(G45:G46) -> 0 | H47: =SUM(H45:H46) -> 0 | I47: =SUM(I45:I46) -> #DIV/0! | J47: =SUM(J45:J46) -> #DIV/0! | K47: =SUM(K45:K46) -> #DIV/0! | ... N47: =SUM(N45:N46) -> #DIV/0!
B48: Total Liabilities | D48: =D44+D47 -> 0 | E48: =E44+E47 -> 0 | F48: =F44+F47 -> 0 | G48: =G44+G47 -> 0 | H48: =H44+H47 -> 0 | I48: =I44+I47 -> #DIV/0! | J48: =J44+J47 -> #DIV/0! | K48: =K44+K47 -> #DIV/0! | ... N48: =N44+N47 -> #DIV/0!
B50: Shareholders' Equity
B51: Total Shareholders' Equity | D51: =D37-D48 -> 0 | E51: =E37-E48 -> 0 | F51: =F37-F48 -> 0 | G51: =G37-G48 -> 0 | H51: =H37-H48 -> 0 | I51: =I316 -> #DIV/0! | J51: =J316 -> #DIV/0! | K51: =K316 -> #DIV/0! | L51: =L316 -> #DIV/0! | M51: =M316 -> #DIV/0! | N51: =N316 -> #DIV/0!
B52: Total Liabilities & Shareholders' Equity | D52: =D51+D48 -> 0 | E52: =E51+E48 -> 0 | F52: =F51+F48 -> 0 | G52: =G51+G48 -> 0 | H52: =H51+H48 -> 0 | I52: =I51+I48 -> #DIV/0! | J52: =J51+J48 -> #DIV/0! | K52: =K51+K48 -> #DIV/0! | ... N52: =N51+N48 -> #DIV/0!
B54: Weighted Average Basic Shares Outstanding | D54: =hist_bal_sht!B55 -> 0 | E54: =hist_bal_sht!C55 -> 0 | F54: =hist_bal_sht!D55 -> 0 | G54: =hist_bal_sht!E55 -> 0 | H54: =hist_bal_sht!F55 -> 0
B57: Statement of Cash Flows | D57: =D10 -> 2020 | E57: =E10 -> 2021 | F57: =F10 -> 2022 | G57: =G10 -> 2023 | H57: =H10 -> 2024 | I57: =H57+1 -> 2025 | J57: =I57+1 -> 2026 | K57: =J57+1 -> 2027 | L57: =K57+1 -> 2028 | M57: =L57+1 -> 2029 | N57: =M57+1 -> 2030
B58: Cash Flow from Operating Activities
B59: Net Income | D59: =hist_scf!B5 -> 0 | E59: =hist_scf!C5 -> 0 | F59: =hist_scf!D5 -> 0 | G59: =hist_scf!E5 -> 0 | H59: =hist_scf!F5 -> 0 | I59: =I23 -> #DIV/0! | J59: =J23 -> #DIV/0! | K59: =K23 -> #DIV/0! | L59: =L23 -> #DIV/0! | M59: =M23 -> #DIV/0! | N59: =N23 -> #DIV/0!
B60: Depreciation | D60: =hist_scf!B6 -> 0 | E60: =hist_scf!C6 -> 0 | F60: =hist_scf!D6 -> 0 | G60: =hist_scf!E6 -> 0 | H60: =hist_scf!F6 -> 0 | I60: =I231 -> #DIV/0! | J60: =J231 -> #DIV/0! | K60: =K231 -> #DIV/0! | L60: =L231 -> #DIV/0! | M60: =M231 -> #DIV/0! | N60: =N231 -> #DIV/0!
B61: Amortization | D61: =hist_scf!B7 -> 0 | E61: =hist_scf!C7 -> 0 | F61: =hist_scf!D7 -> 0 | G61: =hist_scf!E7 -> 0 | H61: =hist_scf!F7 -> 0 | I61: =I237 -> #DIV/0! | J61: =J237 -> #DIV/0! | K61: =K237 -> #DIV/0! | L61: =L237 -> #DIV/0! | M61: =M237 -> #DIV/0! | N61: =N237 -> #DIV/0!
B62: Other operating cash flow | D62: =SUM(hist_scf!B9:B19) -> 0 | E62: =SUM(hist_scf!C9:C19) -> 0 | F62: =SUM(hist_scf!D9:D19) -> 0 | G62: =SUM(hist_scf!E9:E19) -> 0 | H62: =SUM(hist_scf!F9:F19) -> 0 | I62: =I246 -> #DIV/0! | J62: =J246 -> #DIV/0! | K62: =K246 -> #DIV/0! | L62: =L246 -> #DIV/0! | M62: =M246 -> #DIV/0! | N62: =N246 -> #DIV/0!
B63: Cash from Operating | D63: =SUM(D59:D62) -> 0 | E63: =SUM(E59:E62) -> 0 | F63: =SUM(F59:F62) -> 0 | G63: =SUM(G59:G62) -> 0 | H63: =SUM(H59:H62) -> 0 | I63: =SUM(I59:I62) -> #DIV/0! | J63: =SUM(J59:J62) -> #DIV/0! | K63: =SUM(K59:K62) -> #DIV/0! | ... N63: =SUM(N59:N62) -> #DIV/0!
B65: Cash Flow from Investing Activities
B66: Capital expenditures (CAPEX) | D66: =hist_scf!B22 -> 0 | E66: =hist_scf!C22 -> 0 | F66: =hist_scf!D22 -> 0 | G66: =hist_scf!E22 -> 0 | H66: =hist_scf!F22 -> 0 | I66: =I252 -> #DIV/0! | J66: =J252 -> #DIV/0! | K66: =K252 -> #DIV/0! | L66: =L252 -> #DIV/0! | M66: =M252 -> #DIV/0! | N66: =N252 -> #DIV/0!
B67: Other investing cash flow | D67: =SUM(hist_scf!B11:B19) -> 0 | E67: =SUM(hist_scf!C11:C19) -> 0 | F67: =SUM(hist_scf!D11:D19) -> 0 | G67: =SUM(hist_scf!E11:E19) -> 0 | H67: =SUM(hist_scf!F11:F19) -> 0 | I67: =I260 -> #DIV/0! | J67: =J260 -> #DIV/0! | K67: =K260 -> #DIV/0! | L67: =L260 -> #DIV/0! | M67: =M260 -> #DIV/0! | N67: =N260 -> #DIV/0!
B68: Cash from Investing | D68: =SUM(D66:D67) -> 0 | E68: =SUM(E66:E67) -> 0 | F68: =SUM(F66:F67) -> 0 | G68: =SUM(G66:G67) -> 0 | H68: =SUM(H66:H67) -> 0 | I68: =SUM(I66:I67) -> #DIV/0! | J68: =SUM(J66:J67) -> #DIV/0! | K68: =SUM(K66:K67) -> #DIV/0! | ... N68: =SUM(N66:N67) -> #DIV/0!
B70: Cash Flow from Financing Activities
B71: Net debt issued (repaid) | D71: =hist_scf!B32+hist_scf!B35 -> 0 | E71: =hist_scf!C32+hist_scf!C35 -> 0 | F71: =hist_scf!D32+hist_scf!D35 -> 0 | G71: =hist_scf!E32+hist_scf!E35 -> 0 | H71: =hist_scf!F32+hist_scf!F35 -> 0 | I71: =(I41+I45+I42)-(H41+H42+H45) -> #DIV/0! | J71: =(J41+J45+J42)-(I41+I42+I45) -> #DIV/0! | K71: =(K41+K45+K42)-(J41+J42+J45) -> #DIV/0! | L71: =(L41+L45+L42)-(K41+K42+K45) -> #DIV/0! | M71: =(M41+M45+M42)-(L41+L42+L45) -> #DIV/0! | N71: =(N41+N45+N42)-(M41+M42+M45) -> #DIV/0!
B72: Net equity issued (repurchased) | D72: =SUM(hist_scf!B37:B38) -> 0 | E72: =SUM(hist_scf!C37:C38) -> 0 | F72: =SUM(hist_scf!D37:D38) -> 0 | G72: =SUM(hist_scf!E37:E38) -> 0 | H72: =SUM(hist_scf!F37:F38) -> 0 | I72: =I270 -> #DIV/0! | J72: =J270 -> #DIV/0! | K72: =K270 -> #DIV/0! | L72: =L270 -> #DIV/0! | M72: =M270 -> #DIV/0! | N72: =N270 -> #DIV/0!
B73: Dividends | D73: =hist_scf!B41 -> 0 | E73: =hist_scf!C41 -> 0 | F73: =hist_scf!D41 -> 0 | G73: =hist_scf!E41 -> 0 | H73: =hist_scf!F41 -> 0 | I73: =I277 -> #DIV/0! | J73: =J277 -> #DIV/0! | K73: =K277 -> #DIV/0! | L73: =L277 -> #DIV/0! | M73: =M277 -> #DIV/0! | N73: =N277 -> #DIV/0!
B74: Other financing cash flow | D74: =SUM(hist_scf!B43:B44) -> 0 | E74: =SUM(hist_scf!C43:C44) -> 0 | F74: =SUM(hist_scf!D43:D44) -> 0 | G74: =SUM(hist_scf!E43:E44) -> 0 | H74: =SUM(hist_scf!F43:F44) -> 0 | I74: =I281 -> #DIV/0! | J74: =J281 -> #DIV/0! | K74: =K281 -> #DIV/0! | L74: =L281 -> #DIV/0! | M74: =M281 -> #DIV/0! | N74: =N281 -> #DIV/0!
B75: Cash from Financing | D75: =SUM(D71:D74) -> 0 | E75: =SUM(E71:E74) -> 0 | F75: =SUM(F71:F74) -> 0 | G75: =SUM(G71:G74) -> 0 | H75: =SUM(H71:H74) -> 0 | I75: =SUM(I71:I74) -> #DIV/0! | J75: =SUM(J71:J74) -> #DIV/0! | K75: =SUM(K71:K74) -> #DIV/0! | ... N75: =SUM(N71:N74) -> #DIV/0!
B77: Other changes in cash | D77: N/A | E77: =E79-(E63+E68+E75) -> 0 | F77: =F79-(F63+F68+F75) -> 0 | G77: =G79-(G63+G68+G75) -> 0 | H77: =H79-(H63+H68+H75) -> 0 | I77: =I79-(I63+I68+I75) -> #DIV/0! | J77: =J79-(J63+J68+J75) -> #DIV/0! | K77: =K79-(K63+K68+K75) -> #DIV/0! | L77: =L79-(L63+L68+L75) -> #DIV/0! | ... N77: =N79-(N63+N68+N75) -> #DIV/0!
B79: Net increase (decrease) in cash | D79: N/A | E79: =E81-E80 -> 0 | F79: =F81-F80 -> 0 | G79: =G81-G80 -> 0 | H79: =H81-H80 -> 0 | I79: =I81-I80 -> #DIV/0! | J79: =J81-J80 -> #DIV/0! | K79: =K81-K80 -> #DIV/0! | L79: =L81-L80 -> #DIV/0! | ... N79: =N81-N80 -> #DIV/0!
B80: Opening cash balance | D80: N/A | E80: =D81 -> 0 | F80: =E81 -> 0 | G80: =F81 -> 0 | H80: =G81 -> 0 | I80: =H81 -> 0 | J80: =I81 -> #DIV/0! | K80: =J81 -> #DIV/0! | L80: =K81 -> #DIV/0! | ... N80: =M81 -> #DIV/0!
B81: Closing cash balance | D81: =D28 -> 0 | E81: =E28 -> 0 | F81: =F28 -> 0 | G81: =G28 -> 0 | H81: =H28 -> 0 | I81: =I28 -> #DIV/0! | J81: =J28 -> #DIV/0! | K81: =K28 -> #DIV/0! | ... N81: =N28 -> #DIV/0!
B85: Supporting Work | D85: =D10 -> 2020 | E85: =E10 -> 2021 | F85: =F10 -> 2022 | G85: =G10 -> 2023 | H85: =H10 -> 2024 | I85: =H85+1 -> 2025 | J85: =I85+1 -> 2026 | K85: =J85+1 -> 2027 | L85: =K85+1 -> 2028 | M85: =L85+1 -> 2029 | N85: =M85+1 -> 2030
B86: Major Checks
B87: Check: cash > 0 | D87: =D28 -> 0 | E87: =E28 -> 0 | F87: =F28 -> 0 | G87: =G28 -> 0 | H87: =H28 -> 0 | I87: =I28 -> #DIV/0! | J87: =J28 -> #DIV/0! | K87: =K28 -> #DIV/0! | ... N87: =N28 -> #DIV/0!
B88: Check: A - (L + E) = 0 | D88: =D37-(D48+D51) -> 0 | E88: =E37-(E48+E51) -> 0 | F88: =F37-(F48+F51) -> 0 | G88: =G37-(G48+G51) -> 0 | H88: =H37-(H48+H51) -> 0 | I88: =I37-(I48+I51) -> #DIV/0! | J88: =J37-(J48+J51) -> #DIV/0! | K88: =K37-(K48+K51) -> #DIV/0! | ... N88: =N37-(N48+N51) -> #DIV/0!
B89: Check: CAPEX (in SCF) < 0 | D89: =D66 -> 0 | E89: =E66 -> 0 | F89: =F66 -> 0 | G89: =G66 -> 0 | H89: =H66 -> 0 | I89: =I66 -> #DIV/0! | J89: =J66 -> #DIV/0! | K89: =K66 -> #DIV/0! | ... N89: =N66 -> #DIV/0!
B90: Check: (closing cash - beg cash) - (CF oper + CF inv + CF fin + CF other) = 0 | E90: =(E81-E80)-(E63+E68+E75+E77) -> 0 | F90: =(F81-F80)-(F63+F68+F75+F77) -> 0 | G90: =(G81-G80)-(G63+G68+G75+G77) -> 0 | H90: =(H81-H80)-(H63+H68+H75+H77) -> 0 | I90: =(I81-I80)-(I63+I68+I75+I77) -> #DIV/0! | J90: =(J81-J80)-(J63+J68+J75+J77) -> #DIV/0! | K90: =(K81-K80)-(K63+K68+K75+K77) -> #DIV/0! | L90: =(L81-L80)-(L63+L68+L75+L77) -> #DIV/0! | ... N90: =(N81-N80)-(N63+N68+N75+N77) -> #DIV/0!
B91: 1 - profit margin | D91: =(D12+D14+D16+D17+D18+D20)/D11 -> #DIV/0! | E91: =(E12+E14+E16+E17+E18+E20)/E11 -> #DIV/0! | F91: =(F12+F14+F16+F17+F18+F20)/F11 -> #DIV/0! | G91: =(G12+G14+G16+G17+G18+G20)/G11 -> #DIV/0! | H91: =(H12+H14+H16+H17+H18+H20)/H11 -> #DIV/0! | I91: =(I12+I14+I16+I17+I18+I20)/I11 -> #DIV/0! | J91: =(J12+J14+J16+J17+J18+J20)/J11 -> #DIV/0! | K91: =(K12+K14+K16+K17+K18+K20)/K11 -> #DIV/0! | ... N91: =(N12+N14+N16+N17+N18+N20)/N11 -> #DIV/0!
B92: EBITDA/revenue | D92: =(D23-D20-D16+D60+D61)/D11 -> #DIV/0! | E92: =(E23-E20-E16+E60+E61)/E11 -> #DIV/0! | F92: =(F23-F20-F16+F60+F61)/F11 -> #DIV/0! | G92: =(G23-G20-G16+G60+G61)/G11 -> #DIV/0! | H92: =(H23-H20-H16+H60+H61)/H11 -> #DIV/0! | I92: =(I23-I20-I16+I60+I61)/I11 -> #DIV/0! | J92: =(J23-J20-J16+J60+J61)/J11 -> #DIV/0! | K92: =(K23-K20-K16+K60+K61)/K11 -> #DIV/0! | ... N92: =(N23-N20-N16+N60+N61)/N11 -> #DIV/0!
B93: Income Statement
B94: Historic Revenue | D94: =D11 -> 0 | E94: =E11 -> 0 | F94: =F11 -> 0 | G94: =G11 -> 0 | H94: =H11 -> 0 | M94: =(1.55-(3/4)*0.142)/1.55 -> 0.93129032 | N94: Acquisitions share of revenue estimate calculated as (AUM before acquisition - additional AUM from acquisition / total AUM) * (3/4) (3/4 reflects % of the year the company earns revenue based on acquisition date)
B95: Revenue growth | E95: =(E94-D94)/D94 -> #DIV/0! | F95: =(F94-E94)/E94 -> #DIV/0! | G95: =(G94-F94)/F94 -> #DIV/0! | H95: =(M95-G94)/G94 -> #DIV/0! | L95: Revenue growth excluding acquisition (for growth calculation only) | M95: =M94*H11 -> 0 | N95: <- this number is growth of firm without Putnam investment
B96: Revenue growth weight | E96: 0 | F96: 0.2 | G96: 0.3 | H96: 0.5 | I96: =SUM(E96:H96) -> 1 | P96: Test slope calc
B97: Weights * % growth | E97: =E96*E95 -> #DIV/0! | F97: =F96*F95 -> #DIV/0! | G97: =G96*G95 -> #DIV/0! | H97: =H96*H95 -> #DIV/0! | P97: =E94 -> 0 | Q97: =F94 -> 0 | R97: =G94 -> 0 | S97: =M95 -> 0 | X97: =(H94-G94)/G94 -> #DIV/0!
B98: Sum of weights + adjustments | C98: Pennsylvania Trust and Athena Capital and legg mason acquired in 2020 | I98: =SUM(E97:H97) -> #DIV/0! | J98: =I98 -> #DIV/0! | K98: =J98 -> #DIV/0! | L98: =K98 -> #DIV/0! | M98: =L98 -> #DIV/0! | N98: =M98 -> #DIV/0! | P98: 1 | Q98: 2 | R98: 3 | S98: 4
B99: Forecast revenue | I99: =H94*(1+I98) -> #DIV/0! | J99: =I99*(1+J98) -> #DIV/0! | K99: =J99*(1+K98) -> #DIV/0! | L99: =K99*(1+L98) -> #DIV/0! | M99: =L99*(1+M98) -> #DIV/0! | N99: =M99*(1+N98) -> #DIV/0! | P99: Slope (decrease) of revenue between 2021 and 2024 (per year) | X99: =(M95-G94)/G94 -> #DIV/0!
B100: Cost of goods sold | D100: =D12 -> 0 | E100: =E12 -> 0 | F100: =F12 -> 0 | G100: =G12 -> 0 | H100: =H12 -> 0 | P100: =SLOPE(P97:S97,P98:S98) -> 0
B101: COGS/Revenue | D101: =D100/D94 -> #DIV/0! | E101: =E100/E94 -> #DIV/0! | F101: =F100/F94 -> #DIV/0! | G101: =G100/G94 -> #DIV/0! | H101: =H100/H94 -> #DIV/0!
B102: Weights * COGS/Revenue | D102: =D101*0 -> #DIV/0! | E102: =E101*0.1 -> #DIV/0! | F102: =F101*0.2 -> #DIV/0! | G102: =G101*0.3 -> #DIV/0! | H102: =H101*0.4 -> #DIV/0! | I102: =SUM(D102:H102) -> #DIV/0! | J102: decreased COGS/Rev by .25% each year to reflect trending decrease in profitability over historic period
B103: sum of weights | I103: =SUM($D$102:$H$102) -> #DIV/0! | J103: =I103-0.25% -> #DIV/0! | K103: =J103-0.25% -> #DIV/0! | L103: =K103-0.25% -> #DIV/0! | M103: =L103-0.25% -> #DIV/0! | N103: =M103-0.25% -> #DIV/0!
B104: Forecast cost of goods sold | I104: =I103*I11 -> #DIV/0! | J104: =J103*J11 -> #DIV/0! | K104: =K103*K11 -> #DIV/0! | L104: =L103*L11 -> #DIV/0! | M104: =M103*M11 -> #DIV/0! | N104: =N103*N11 -> #DIV/0!
B107: SG&A | D107: =D14 -> 0 | E107: =E14 -> 0 | F107: =F14 -> 0 | G107: =G14 -> 0 | H107: =H14 -> 0
B108: SG&A/Revenue | D108: =D107/D11 -> #DIV/0! | E108: =E107/E11 -> #DIV/0! | F108: =F107/F11 -> #DIV/0! | G108: =G107/G11 -> #DIV/0! | H108: =H107/H11 -> #DIV/0!
B109: Weight * SG&A/Revenue | D109: =D108*0 -> #DIV/0! | E109: =E108*0.1 -> #DIV/0! | F109: =F108*0.2 -> #DIV/0! | G109: =G108*0.3 -> #DIV/0! | H109: =H108*0.4 -> #DIV/0! | I109: =SUM(D109:H109) -> #DIV/0! | J109: decreased SG&A/Rev by .5% each year to reflect trending decrease in profitability over historic period
B110: Average SG&A/revenue + adjustments | I110: =SUM($D$109:$H$109) -> #DIV/0! | J110: =I110-0.5% -> #DIV/0! | K110: =J110-0.5% -> #DIV/0! | L110: =K110-0.5% -> #DIV/0! | M110: =L110-0.5% -> #DIV/0! | N110: =M110-0.5% -> #DIV/0!
I111: =I110*I11 -> #DIV/0! | J111: =J110*J11 -> #DIV/0! | K111: =K110*K11 -> #DIV/0! | L111: =L110*L11 -> #DIV/0! | M111: =M110*M11 -> #DIV/0! | N111: =N110*N11 -> #DIV/0!
B113: Interest | D113: =D16 -> 0 | E113: =E16 -> 0 | F113: =F16 -> 0 | G113: =G16 -> 0 | H113: =H16 -> 0
B114: Total debt | E114: =SUM(E41,E42,E45) -> 0 | F114: =SUM(F41,F42,F45) -> 0 | G114: =SUM(G41,G42,G45) -> 0 | H114: =SUM(H41,H42,H45) -> 0
B115: Implied interest rate | E115: =E113/E114 -> #DIV/0! | F115: =F113/F114 -> #DIV/0! | G115: =G113/G114 -> #DIV/0! | H115: =H113/H114 -> #DIV/0!
B116: Average implied interest rate | I116: =AVERAGE(E115:H115) -> #DIV/0!
B117: Forecast total debt | I117: =I41+I42+I45 -> #DIV/0! | J117: =J41+J42+J45 -> #DIV/0! | K117: =K41+K42+K45 -> #DIV/0! | L117: =L41+L42+L45 -> #DIV/0! | M117: =M41+M42+M45 -> #DIV/0! | N117: =N41+N42+N45 -> #DIV/0!
B118: Forecast interest | I118: =$I116*I117 -> #DIV/0! | J118: =$I116*J117 -> #DIV/0! | K118: =$I116*K117 -> #DIV/0! | L118: =$I116*L117 -> #DIV/0! | M118: =$I116*M117 -> #DIV/0! | N118: =$I116*N117 -> #DIV/0!
B120: =B17 -> Other non-operating income (expense) except interest expense & unusual | D120: =D17 -> 0 | E120: =E17 -> 0 | F120: =F17 -> 0 | G120: =G17 -> 0 | H120: =H17 -> 0
B121: Non-operating income/ Revenue | D121: =D120/D11 -> #DIV/0! | E121: =E120/E11 -> #DIV/0! | F121: =F120/F11 -> #DIV/0! | G121: =G120/G11 -> #DIV/0! | H121: =H120/H11 -> #DIV/0!
...

Sheet model_drivers
B2: Last Historic Year | C2: Forecast year 1 | D2: Forecast year 2 | E2: Forecast year 3 | F2: Forecast year 4 | G2: Forecast year 5 | H2: Forecast year 6
A3: Income statement
A4: Revenue growth rate | B4: =fin_model!X97 -> #DIV/0! | C4: =fin_model!I98 -> #DIV/0! | D4: =fin_model!J98 -> #DIV/0! | E4: =fin_model!K98 -> #DIV/0! | F4: =fin_model!L98 -> #DIV/0! | G4: =fin_model!M98 -> #DIV/0! | H4: =fin_model!N98 -> #DIV/0!
A5: COGS to sales | B5: =fin_model!H12/fin_model!H11 -> #DIV/0! | C5: =fin_model!I12/fin_model!I11 -> #DIV/0! | D5: =fin_model!J12/fin_model!J11 -> #DIV/0! | E5: =fin_model!K12/fin_model!K11 -> #DIV/0! | F5: =fin_model!L12/fin_model!L11 -> #DIV/0! | G5: =fin_model!M12/fin_model!M11 -> #DIV/0! | H5: =fin_model!N12/fin_model!N11 -> #DIV/0!
A6: SG&A & other indirect expenses to sales | B6: =fin_model!H14/fin_model!H11 -> #DIV/0! | C6: =fin_model!I14/fin_model!I11 -> #DIV/0! | D6: =fin_model!J14/fin_model!J11 -> #DIV/0! | E6: =fin_model!K14/fin_model!K11 -> #DIV/0! | F6: =fin_model!L14/fin_model!L11 -> #DIV/0! | G6: =fin_model!M14/fin_model!M11 -> #DIV/0! | H6: =fin_model!N14/fin_model!N11 -> #DIV/0!
A7: Implied interest rate | B7: =fin_model!$I116 -> #DIV/0! | C7: =fin_model!$I116 -> #DIV/0! | D7: =fin_model!$I116 -> #DIV/0! | E7: =fin_model!$I116 -> #DIV/0! | F7: =fin_model!$I116 -> #DIV/0! | G7: =fin_model!$I116 -> #DIV/0! | H7: =fin_model!$I116 -> #DIV/0!
A8: All other non-operating income (expense) to sales | B8: =fin_model!H17/fin_model!H11 -> #DIV/0! | C8: =fin_model!I17/fin_model!I11 -> #DIV/0! | D8: =fin_model!J17/fin_model!J11 -> #DIV/0! | E8: =fin_model!K17/fin_model!K11 -> #DIV/0! | F8: =fin_model!L17/fin_model!L11 -> #DIV/0! | G8: =fin_model!M17/fin_model!M11 -> #DIV/0! | H8: =fin_model!N17/fin_model!N11 -> #DIV/0!
A9: Unusual items to sales | B9: =fin_model!H18/fin_model!H11 -> #DIV/0! | C9: =fin_model!I18/fin_model!I11 -> #DIV/0! | D9: =fin_model!J18/fin_model!J11 -> #DIV/0! | E9: =fin_model!K18/fin_model!K11 -> #DIV/0! | F9: =fin_model!L18/fin_model!L11 -> #DIV/0! | G9: =fin_model!M18/fin_model!M11 -> #DIV/0! | H9: =fin_model!N18/fin_model!N11 -> #DIV/0!
A10: Effective tax rate | B10: =fin_model!$I132 -> #DIV/0! | C10: =fin_model!$I132 -> #DIV/0! | D10: =fin_model!$I132 -> #DIV/0! | E10: =fin_model!$I132 -> #DIV/0! | F10: =fin_model!$I132 -> #DIV/0! | G10: =fin_model!$I132 -> #DIV/0! | H10: =fin_model!$I132 -> #DIV/0!
A11: Other considerations to sales | B11: =fin_model!H22/fin_model!H11 -> #DIV/0! | C11: =fin_model!I22/fin_model!I11 -> #DIV/0! | D11: =fin_model!J22/fin_model!J11 -> #DIV/0! | E11: =fin_model!K22/fin_model!K11 -> #DIV/0! | F11: =fin_model!L22/fin_model!L11 -> #DIV/0! | G11: =fin_model!M22/fin_model!M11 -> #DIV/0! | H11: =fin_model!N22/fin_model!N11 -> #DIV/0!
A12: Balance sheet
A13: Other nonoperating current assets to sales | B13: =fin_model!H29/fin_model!H11 -> #DIV/0! | C13: =fin_model!I29/fin_model!I11 -> #DIV/0! | D13: =fin_model!J29/fin_model!J11 -> #DIV/0! | E13: =fin_model!K29/fin_model!K11 -> #DIV/0! | F13: =fin_model!L29/fin_model!L11 -> #DIV/0! | G13: =fin_model!M29/fin_model!M11 -> #DIV/0! | H13: =fin_model!N29/fin_model!N11 -> #DIV/0!
A14: Receivables to sales | B14: =fin_model!H30/fin_model!H11 -> #DIV/0! | C14: =fin_model!I30/fin_model!I11 -> #DIV/0! | D14: =fin_model!J30/fin_model!J11 -> #DIV/0! | E14: =fin_model!K30/fin_model!K11 -> #DIV/0! | F14: =fin_model!L30/fin_model!L11 -> #DIV/0! | G14: =fin_model!M30/fin_model!M11 -> #DIV/0! | H14: =fin_model!N30/fin_model!N11 -> #DIV/0!
A15: Inventory to COGS | B15: =fin_model!H31/fin_model!H12 -> #DIV/0! | C15: =fin_model!I31/fin_model!I12 -> #DIV/0! | D15: =fin_model!J31/fin_model!J12 -> #DIV/0! | E15: =fin_model!K31/fin_model!K12 -> #DIV/0! | F15: =fin_model!L31/fin_model!L12 -> #DIV/0! | G15: =fin_model!M31/fin_model!M12 -> #DIV/0! | H15: =fin_model!N31/fin_model!N12 -> #DIV/0!
A16: Other operating current assets to sales | B16: =fin_model!H32/fin_model!H11 -> #DIV/0! | C16: =fin_model!I32/fin_model!I11 -> #DIV/0! | D16: =fin_model!J32/fin_model!J11 -> #DIV/0! | E16: =fin_model!K32/fin_model!K11 -> #DIV/0! | F16: =fin_model!L32/fin_model!L11 -> #DIV/0! | G16: =fin_model!M32/fin_model!M11 -> #DIV/0! | H16: =fin_model!N32/fin_model!N11 -> #DIV/0!
A17: Depreciation to sales (relevant for PP&E and SCF) | B17: =fin_model!H60/fin_model!H11 -> #DIV/0! | C17: =fin_model!I60/fin_model!I11 -> #DIV/0! | D17: =fin_model!J60/fin_model!J11 -> #DIV/0! | E17: =fin_model!K60/fin_model!K11 -> #DIV/0! | F17: =fin_model!L60/fin_model!L11 -> #DIV/0! | G17: =fin_model!M60/fin_model!M11 -> #DIV/0! | H17: =fin_model!N60/fin_model!N11 -> #DIV/0!
A18: CAPEX CF to sales (relevant for PP&E and SCF) - CF, so should be negative | B18: =fin_model!H66/fin_model!H11 -> #DIV/0! | C18: =fin_model!I66/fin_model!I11 -> #DIV/0! | D18: =fin_model!J66/fin_model!J11 -> #DIV/0! | E18: =fin_model!K66/fin_model!K11 -> #DIV/0! | F18: =fin_model!L66/fin_model!L11 -> #DIV/0! | G18: =fin_model!M66/fin_model!M11 -> #DIV/0! | H18: =fin_model!N66/fin_model!N11 -> #DIV/0!
A19: Other long-term assets to sales | B19: =fin_model!H35/fin_model!H11 -> #DIV/0! | C19: =fin_model!I35/fin_model!I11 -> #DIV/0! | D19: =fin_model!J35/fin_model!J11 -> #DIV/0! | E19: =fin_model!K35/fin_model!K11 -> #DIV/0! | F19: =fin_model!L35/fin_model!L11 -> #DIV/0! | G19: =fin_model!M35/fin_model!M11 -> #DIV/0! | H19: =fin_model!N35/fin_model!N11 -> #DIV/0!
A20: Payables to COGS | B20: =fin_model!H40/fin_model!H12 -> #DIV/0! | C20: =fin_model!I40/fin_model!I12 -> #DIV/0! | D20: =fin_model!J40/fin_model!J12 -> #DIV/0! | E20: =fin_model!K40/fin_model!K12 -> #DIV/0! | F20: =fin_model!L40/fin_model!L12 -> #DIV/0! | G20: =fin_model!M40/fin_model!M12 -> #DIV/0! | H20: =fin_model!N40/fin_model!N12 -> #DIV/0!
A21: Amount of short-term debt | B21: =fin_model!H41 -> 0 | C21: =fin_model!I41 -> 0 | D21: =fin_model!J41 -> 0 | E21: =fin_model!K41 -> 0 | F21: =fin_model!L41 -> 0 | G21: =fin_model!M41 -> 0 | H21: =fin_model!N41 -> 0
A22: Amount of current portion of long-term debt | B22: =fin_model!H42 -> 0 | C22: =fin_model!I42 -> 400 | D22: =fin_model!J42 -> 469.5 | E22: =fin_model!K42 -> 0 | F22: =fin_model!L42 -> 0 | G22: =fin_model!M42 -> 0 | H22: =fin_model!N42 -> 847.5
A23: Other current liabilities to sales | B23: =fin_model!H43/fin_model!H11 -> #DIV/0! | C23: =fin_model!I43/fin_model!I11 -> #DIV/0! | D23: =fin_model!J43/fin_model!J11 -> #DIV/0! | E23: =fin_model!K43/fin_model!K11 -> #DIV/0! | F23: =fin_model!L43/fin_model!L11 -> #DIV/0! | G23: =fin_model!M43/fin_model!M11 -> #DIV/0! | H23: =fin_model!N43/fin_model!N11 -> #DIV/0!
A24: Amount of long-term debt in LT liabilities | B24: =fin_model!H45 -> 0 | C24: =fin_model!I45 -> #DIV/0! | D24: =fin_model!J45 -> #DIV/0! | E24: =fin_model!K45 -> #DIV/0! | F24: =fin_model!L45 -> #DIV/0! | G24: =fin_model!M45 -> #DIV/0! | H24: =fin_model!N45 -> #DIV/0!
A25: Other long-term liabilities to sales | B25: =fin_model!H46/fin_model!H11 -> #DIV/0! | C25: =fin_model!I46/fin_model!I11 -> #DIV/0! | D25: =fin_model!J46/fin_model!J11 -> #DIV/0! | E25: =fin_model!K46/fin_model!K11 -> #DIV/0! | F25: =fin_model!L46/fin_model!L11 -> #DIV/0! | G25: =fin_model!M46/fin_model!M11 -> #DIV/0! | H25: =fin_model!N46/fin_model!N11 -> #DIV/0!
A26: Dividend cash flow in first forecast year | B26: =fin_model!H73 -> 0 | C26: =fin_model!I73 -> #DIV/0!
A27: Dividend growth rate | D27: =(fin_model!J73-fin_model!I73)/fin_model!I73 -> #DIV/0! | E27: =(fin_model!K73-fin_model!J73)/fin_model!J73 -> #DIV/0! | F27: =(fin_model!L73-fin_model!K73)/fin_model!K73 -> #DIV/0! | G27: =(fin_model!M73-fin_model!L73)/fin_model!L73 -> #DIV/0! | H27: =(fin_model!N73-fin_model!M73)/fin_model!M73 -> #DIV/0!
A28: Net equity issued (repurchased) to sales | B28: =fin_model!H72/fin_model!H11 -> #DIV/0! | C28: =fin_model!I72/fin_model!I11 -> #DIV/0! | D28: =fin_model!J72/fin_model!J11 -> #DIV/0! | E28: =fin_model!K72/fin_model!K11 -> #DIV/0! | F28: =fin_model!L72/fin_model!L11 -> #DIV/0! | G28: =fin_model!M72/fin_model!M11 -> #DIV/0! | H28: =fin_model!N72/fin_model!N11 -> #DIV/0!
A29: All other relevant equity change items to sales | B29: =fin_model!H315/fin_model!H11 -> #DIV/0! | C29: =fin_model!I315/fin_model!I11 -> #DIV/0! | D29: =fin_model!J315/fin_model!J11 -> #DIV/0! | E29: =fin_model!K315/fin_model!K11 -> #DIV/0! | F29: =fin_model!L315/fin_model!L11 -> #DIV/0! | G29: =fin_model!M315/fin_model!M11 -> #DIV/0! | H29: =fin_model!N315/fin_model!N11 -> #DIV/0!
A30: Statement of cash flows
A31: Amortization to sales | B31: =fin_model!H61/fin_model!H11 -> #DIV/0! | C31: =fin_model!I61/fin_model!I11 -> #DIV/0! | D31: =fin_model!J61/fin_model!J11 -> #DIV/0! | E31: =fin_model!K61/fin_model!K11 -> #DIV/0! | F31: =fin_model!L61/fin_model!L11 -> #DIV/0! | G31: =fin_model!M61/fin_model!M11 -> #DIV/0! | H31: =fin_model!N61/fin_model!N11 -> #DIV/0!
A32: Other operating cash flow to sales | B32: =fin_model!H62/fin_model!H11 -> #DIV/0! | C32: =fin_model!I62/fin_model!I11 -> #DIV/0! | D32: =fin_model!J62/fin_model!J11 -> #DIV/0! | E32: =fin_model!K62/fin_model!K11 -> #DIV/0! | F32: =fin_model!L62/fin_model!L11 -> #DIV/0! | G32: =fin_model!M62/fin_model!M11 -> #DIV/0! | H32: =fin_model!N62/fin_model!N11 -> #DIV/0!
A33: Other investing cash flow to sales | B33: =fin_model!H67/fin_model!H11 -> #DIV/0! | C33: =fin_model!I67/fin_model!I11 -> #DIV/0! | D33: =fin_model!J67/fin_model!J11 -> #DIV/0! | E33: =fin_model!K67/fin_model!K11 -> #DIV/0! | F33: =fin_model!L67/fin_model!L11 -> #DIV/0! | G33: =fin_model!M67/fin_model!M11 -> #DIV/0! | H33: =fin_model!N67/fin_model!N11 -> #DIV/0!
A34: Other financing cash flow to sales | B34: =fin_model!H74/fin_model!H11 -> #DIV/0! | C34: =fin_model!I74/fin_model!I11 -> #DIV/0! | D34: =fin_model!J74/fin_model!J11 -> #DIV/0! | E34: =fin_model!K74/fin_model!K11 -> #DIV/0! | F34: =fin_model!L74/fin_model!L11 -> #DIV/0! | G34: =fin_model!M74/fin_model!M11 -> #DIV/0! | H34: =fin_model!N74/fin_model!N11 -> #DIV/0!

Sheet fsa_measures
A3: Financial statement analysis for firm: historical & forecast
B4: Historical period | G4: Forecast period
B5: =fin_model!D10 -> 2020 | C5: =B5+1 -> 2021 | D5: =C5+1 -> 2022 | E5: =D5+1 -> 2023 | F5: =E5+1 -> 2024 | G5: =F5+1 -> 2025 | H5: =G5+1 -> 2026 | I5: =H5+1 -> 2027 | J5: =I5+1 -> 2028 | ... L5: =K5+1 -> 2030
B6: Liquidity
A7: Current ratio | B7: =fin_model!D33/fin_model!D44 -> #DIV/0! | C7: =fin_model!E33/fin_model!E44 -> #DIV/0! | D7: =fin_model!F33/fin_model!F44 -> #DIV/0! | E7: =fin_model!G33/fin_model!G44 -> #DIV/0! | F7: =fin_model!H33/fin_model!H44 -> #DIV/0! | G7: =fin_model!I33/fin_model!I44 -> #DIV/0! | H7: =fin_model!J33/fin_model!J44 -> #DIV/0! | I7: =fin_model!K33/fin_model!K44 -> #DIV/0! | ... L7: =fin_model!N33/fin_model!N44 -> #DIV/0!
A8: Quick ratio | B8: =(fin_model!D33-fin_model!D31)/fin_model!D44 -> #DIV/0! | C8: =(fin_model!E33-fin_model!E31)/fin_model!E44 -> #DIV/0! | D8: =(fin_model!F33-fin_model!F31)/fin_model!F44 -> #DIV/0! | E8: =(fin_model!G33-fin_model!G31)/fin_model!G44 -> #DIV/0! | F8: =(fin_model!H33-fin_model!H31)/fin_model!H44 -> #DIV/0! | G8: =(fin_model!I33-fin_model!I31)/fin_model!I44 -> #DIV/0! | H8: =(fin_model!J33-fin_model!J31)/fin_model!J44 -> #DIV/0! | I8: =(fin_model!K33-fin_model!K31)/fin_model!K44 -> #DIV/0! | ... L8: =(fin_model!N33-fin_model!N31)/fin_model!N44 -> #DIV/0!
B9: Solvency
A10: Times interest earned (from EBIT) | B10: =-(fin_model!D15/fin_model!D16) -> #DIV/0! | C10: =-(fin_model!E15/fin_model!E16) -> #DIV/0! | D10: =-(fin_model!F15/fin_model!F16) -> #DIV/0! | E10: =-(fin_model!G15/fin_model!G16) -> #DIV/0! | F10: =-(fin_model!H15/fin_model!H16) -> #DIV/0! | G10: =-(fin_model!I15/fin_model!I16) -> #DIV/0! | H10: =-(fin_model!J15/fin_model!J16) -> #DIV/0! | I10: =-(fin_model!K15/fin_model!K16) -> #DIV/0! | ... L10: =-(fin_model!N15/fin_model!N16) -> #DIV/0!
B11: Leverage
A12: Debt to assets ratio | B12: =SUM(fin_model!D41,fin_model!D42,fin_model!D45)/fin_model!D37 -> #DIV/0! | C12: =SUM(fin_model!E41,fin_model!E42,fin_model!E45)/fin_model!E37 -> #DIV/0! | D12: =SUM(fin_model!F41,fin_model!F42,fin_model!F45)/fin_model!F37 -> #DIV/0! | E12: =SUM(fin_model!G41,fin_model!G42,fin_model!G45)/fin_model!G37 -> #DIV/0! | F12: =SUM(fin_model!H41,fin_model!H42,fin_model!H45)/fin_model!H37 -> #DIV/0! | G12: =SUM(fin_model!I41,fin_model!I42,fin_model!I45)/fin_model!I37 -> #DIV/0! | H12: =SUM(fin_model!J41,fin_model!J42,fin_model!J45)/fin_model!J37 -> #DIV/0! | I12: =SUM(fin_model!K41,fin_model!K42,fin_model!K45)/fin_model!K37 -> #DIV/0! | ... L12: =SUM(fin_model!N41,fin_model!N42,fin_model!N45)/fin_model!N37 -> #DIV/0!
A13: Debt to Equity Ratio | B13: =SUM(fin_model!D41,fin_model!D42,fin_model!D45)/fin_model!D51 -> #DIV/0! | C13: =SUM(fin_model!E41,fin_model!E42,fin_model!E45)/fin_model!E51 -> #DIV/0! | D13: =SUM(fin_model!F41,fin_model!F42,fin_model!F45)/fin_model!F51 -> #DIV/0! | E13: =SUM(fin_model!G41,fin_model!G42,fin_model!G45)/fin_model!G51 -> #DIV/0! | F13: =SUM(fin_model!H41,fin_model!H42,fin_model!H45)/fin_model!H51 -> #DIV/0! | G13: =SUM(fin_model!I41,fin_model!I42,fin_model!I45)/fin_model!I51 -> #DIV/0! | H13: =SUM(fin_model!J41,fin_model!J42,fin_model!J45)/fin_model!J51 -> #DIV/0! | I13: =SUM(fin_model!K41,fin_model!K42,fin_model!K45)/fin_model!K51 -> #DIV/0! | ... L13: =SUM(fin_model!N41,fin_model!N42,fin_model!N45)/fin_model!N51 -> #DIV/0!
B14: Efficiency
A15: Asset turnover | B15: =fin_model!D11/fin_model!D37 -> #DIV/0! | C15: =fin_model!E11/fin_model!E37 -> #DIV/0! | D15: =fin_model!F11/fin_model!F37 -> #DIV/0! | E15: =fin_model!G11/fin_model!G37 -> #DIV/0! | F15: =fin_model!H11/fin_model!H37 -> #DIV/0! | G15: =fin_model!I11/fin_model!I37 -> #DIV/0! | H15: =fin_model!J11/fin_model!J37 -> #DIV/0! | I15: =fin_model!K11/fin_model!K37 -> #DIV/0! | ... L15: =fin_model!N11/fin_model!N37 -> #DIV/0!
A16: Receivables days | B16: =(365/(fin_model!D11/fin_model!D30)) -> #DIV/0! | C16: =(365/(fin_model!E11/fin_model!E30)) -> #DIV/0! | D16: =(365/(fin_model!F11/fin_model!F30)) -> #DIV/0! | E16: =(365/(fin_model!G11/fin_model!G30)) -> #DIV/0! | F16: =(365/(fin_model!H11/fin_model!H30)) -> #DIV/0! | G16: =(365/(fin_model!I11/fin_model!I30)) -> #DIV/0! | H16: =(365/(fin_model!J11/fin_model!J30)) -> #DIV/0! | I16: =(365/(fin_model!K11/fin_model!K30)) -> #DIV/0! | ... L16: =(365/(fin_model!N11/fin_model!N30)) -> #DIV/0!
A17: Payables days | B17: =-365/(fin_model!D12/fin_model!D40) -> #DIV/0! | C17: =-365/(fin_model!E12/fin_model!E40) -> #DIV/0! | D17: =-365/(fin_model!F12/fin_model!F40) -> #DIV/0! | E17: =-365/(fin_model!G12/fin_model!G40) -> #DIV/0! | F17: =-365/(fin_model!H12/fin_model!H40) -> #DIV/0! | G17: =-365/(fin_model!I12/fin_model!I40) -> #DIV/0! | H17: =-365/(fin_model!J12/fin_model!J40) -> #DIV/0! | I17: =-365/(fin_model!K12/fin_model!K40) -> #DIV/0! | ... L17: =-365/(fin_model!N12/fin_model!N40) -> #DIV/0!
B18: Profitability
A19: Gross Margin | B19: =(fin_model!D13/fin_model!D11) -> #DIV/0! | C19: =(fin_model!E13/fin_model!E11) -> #DIV/0! | D19: =(fin_model!F13/fin_model!F11) -> #DIV/0! | E19: =(fin_model!G13/fin_model!G11) -> #DIV/0! | F19: =(fin_model!H13/fin_model!H11) -> #DIV/0! | G19: =(fin_model!I13/fin_model!I11) -> #DIV/0! | H19: =(fin_model!J13/fin_model!J11) -> #DIV/0! | I19: =(fin_model!K13/fin_model!K11) -> #DIV/0! | ... L19: =(fin_model!N13/fin_model!N11) -> #DIV/0!
A20: Operating profit margin | B20: =fin_model!D15/fin_model!D11 -> #DIV/0! | C20: =fin_model!E15/fin_model!E11 -> #DIV/0! | D20: =fin_model!F15/fin_model!F11 -> #DIV/0! | E20: =fin_model!G15/fin_model!G11 -> #DIV/0! | F20: =fin_model!H15/fin_model!H11 -> #DIV/0! | G20: =fin_model!I15/fin_model!I11 -> #DIV/0! | H20: =fin_model!J15/fin_model!J11 -> #DIV/0! | I20: =fin_model!K15/fin_model!K11 -> #DIV/0! | ... L20: =fin_model!N15/fin_model!N11 -> #DIV/0!
A21: Net profit margin | B21: =fin_model!D23/fin_model!D11 -> #DIV/0! | C21: =fin_model!E23/fin_model!E11 -> #DIV/0! | D21: =fin_model!F23/fin_model!F11 -> #DIV/0! | E21: =fin_model!G23/fin_model!G11 -> #DIV/0! | F21: =fin_model!H23/fin_model!H11 -> #DIV/0! | G21: =fin_model!I23/fin_model!I11 -> #DIV/0! | H21: =fin_model!J23/fin_model!J11 -> #DIV/0! | I21: =fin_model!K23/fin_model!K11 -> #DIV/0! | ... L21: =fin_model!N23/fin_model!N11 -> #DIV/0!
A22: Return on assets | B22: =fin_model!D23/fin_model!D37 -> #DIV/0! | C22: =((fin_model!E23+fin_model!F23)/2)/fin_model!E37 -> #DIV/0! | D22: =((fin_model!F23+fin_model!G23)/2)/fin_model!F37 -> #DIV/0! | E22: =((fin_model!G23+fin_model!H23)/2)/fin_model!G37 -> #DIV/0! | F22: =((fin_model!H23+fin_model!I23)/2)/fin_model!H37 -> #DIV/0! | G22: =((fin_model!I23+fin_model!H23)/2)/fin_model!I37 -> #DIV/0! | H22: =((fin_model!J23+fin_model!I23)/2)/fin_model!J37 -> #DIV/0! | I22: =((fin_model!K23+fin_model!J23)/2)/fin_model!K37 -> #DIV/0! | J22: =((fin_model!L23+fin_model!K23)/2)/fin_model!L37 -> #DIV/0! | K22: =((fin_model!M23+fin_model!L23)/2)/fin_model!M37 -> #DIV/0! | L22: =((fin_model!N23+fin_model!M23)/2)/fin_model!N37 -> #DIV/0!
A23: Return on invested capital based on a 22.5% tax rate | B23: =(fin_model!D15*(1-0.225))/SUM(fin_model!D41,fin_model!D42,fin_model!D45,fin_model!D51) -> #DIV/0! | C23: =(fin_model!E15*(1-0.225))/SUM(fin_model!E41,fin_model!E42,fin_model!E45,fin_model!E51) -> #DIV/0! | D23: =(fin_model!F15*(1-0.225))/SUM(fin_model!F41,fin_model!F42,fin_model!F45,fin_model!F51) -> #DIV/0! | E23: =(fin_model!G15*(1-0.225))/SUM(fin_model!G41,fin_model!G42,fin_model!G45,fin_model!G51) -> #DIV/0! | F23: =(fin_model!H15*(1-0.225))/SUM(fin_model!H41,fin_model!H42,fin_model!H45,fin_model!H51) -> #DIV/0! | G23: =(fin_model!I15*(1-0.225))/SUM(fin_model!I41,fin_model!I42,fin_model!I45,fin_model!I51) -> #DIV/0! | H23: =(fin_model!J15*(1-0.225))/SUM(fin_model!J41,fin_model!J42,fin_model!J45,fin_model!J51) -> #DIV/0! | I23: =(fin_model!K15*(1-0.225))/SUM(fin_model!K41,fin_model!K42,fin_model!K45,fin_model!K51) -> #DIV/0! | ... L23: =(fin_model!N15*(1-0.225))/SUM(fin_model!N41,fin_model!N42,fin_model!N45,fin_model!N51) -> #DIV/0!
A26: Working capital funding gap | B26: =IFERROR(B28+B16-B17,"N/A") -> N/A | C26: =IFERROR(C28+C16-C17,"N/A") -> N/A | D26: =IFERROR(D28+D16-D17,"N/A") -> N/A | E26: =IFERROR(E28+E16-E17,"N/A") -> N/A | F26: =IFERROR(F28+F16-F17,"N/A") -> N/A | G26: =IFERROR(G28+G16-G17,"N/A") -> N/A | H26: =IFERROR(H28+H16-H17,"N/A") -> N/A | I26: =IFERROR(I28+I16-I17,"N/A") -> N/A | ... L26: =IFERROR(L28+L16-L17,"N/A") -> N/A
A28: Inventory days | B28: =IFERROR(-365/(fin_model!D12/fin_model!D31), "No Inventory") -> No Inventory | C28: =IFERROR(-365/(fin_model!E12/fin_model!E31), "No Inventory") -> No Inventory | D28: =IFERROR(-365/(fin_model!F12/fin_model!F31), "No Inventory") -> No Inventory | E28: =IFERROR(-365/(fin_model!G12/fin_model!G31), "No Inventory") -> No Inventory | F28: =IFERROR(-365/(fin_model!H12/fin_model!H31), "No Inventory") -> No Inventory | G28: =IFERROR(-365/(fin_model!I12/fin_model!I31), "No Inventory") -> No Inventory | H28: =IFERROR(-365/(fin_model!J12/fin_model!J31), "No Inventory") -> No Inventory | I28: =IFERROR(-365/(fin_model!K12/fin_model!K31), "No Inventory") -> No Inventory | ... L28: =IFERROR(-365/(fin_model!N12/fin_model!N31), "No Inventory") -> No Inventory
S34: Historic Period | W34: =G4 -> Forecast period
S35: =C5 -> 2021 | T35: =D5 -> 2022 | U35: =E5 -> 2023 | V35: =F5 -> 2024 | W35: =G5 -> 2025 | X35: =H5 -> 2026 | Y35: =I5 -> 2027 | Z35: =J5 -> 2028 | ... AB35: =L5 -> 2030
S36: Profitability
R37: =A19 -> Gross Margin | S37: =C19 -> #DIV/0! | T37: =D19 -> #DIV/0! | U37: =E19 -> #DIV/0! | V37: =F19 -> #DIV/0! | W37: =G19 -> #DIV/0! | X37: =H19 -> #DIV/0! | Y37: =I19 -> #DIV/0! | Z37: =J19 -> #DIV/0! | ... AB37: =L19 -> #DIV/0!
R38: =A20 -> Operating profit margin | S38: =C20 -> #DIV/0! | T38: =D20 -> #DIV/0! | U38: =E20 -> #DIV/0! | V38: =F20 -> #DIV/0! | W38: =G20 -> #DIV/0! | X38: =H20 -> #DIV/0! | Y38: =I20 -> #DIV/0! | Z38: =J20 -> #DIV/0! | ... AB38: =L20 -> #DIV/0!
R39: =A21 -> Net profit margin | S39: =C21 -> #DIV/0! | T39: =D21 -> #DIV/0! | U39: =E21 -> #DIV/0! | V39: =F21 -> #DIV/0! | W39: =G21 -> #DIV/0! | X39: =H21 -> #DIV/0! | Y39: =I21 -> #DIV/0! | Z39: =J21 -> #DIV/0! | ... AB39: =L21 -> #DIV/0!
S40: Liquidity
R41: =A7 -> Current ratio | S41: =C7 -> #DIV/0! | T41: =D7 -> #DIV/0! | U41: =E7 -> #DIV/0! | V41: =F7 -> #DIV/0! | W41: =G7 -> #DIV/0! | X41: =H7 -> #DIV/0! | Y41: =I7 -> #DIV/0! | Z41: =J7 -> #DIV/0! | ... AB41: =L7 -> #DIV/0!
R42: =A8 -> Quick ratio | S42: =C8 -> #DIV/0! | T42: =D8 -> #DIV/0! | U42: =E8 -> #DIV/0! | V42: =F8 -> #DIV/0! | W42: =G8 -> #DIV/0! | X42: =H8 -> #DIV/0! | Y42: =I8 -> #DIV/0! | Z42: =J8 -> #DIV/0! | ... AB42: =L8 -> #DIV/0!
S43: Leverage
R44: =A12 -> Debt to assets ratio | S44: =C12 -> #DIV/0! | T44: =D12 -> #DIV/0! | U44: =E12 -> #DIV/0! | V44: =F12 -> #DIV/0! | W44: =G12 -> #DIV/0! | X44: =H12 -> #DIV/0! | Y44: =I12 -> #DIV/0! | Z44: =J12 -> #DIV/0! | ... AB44: =L12 -> #DIV/0!
R45: Debt to Equity Ratio | S45: =C13 -> #DIV/0! | T45: =D13 -> #DIV/0! | U45: =E13 -> #DIV/0! | V45: =F13 -> #DIV/0! | W45: =G13 -> #DIV/0! | X45: =H13 -> #DIV/0! | Y45: =I13 -> #DIV/0! | Z45: =J13 -> #DIV/0! | ... AB45: =L13 -> #DIV/0!

Sheet mergent_raw
A4: Powered by Clearbit
A5: Franklin Resources Inc (NYS: BEN)
A8: General Company Information
A9: Principal Office | B9: Website
A10: One Franklin Parkway San Mateo, CA 94403 USA | B10: www.franklinresources.com
A12: Phone | B12: Primary NAICS
A13: 650 312-2000 | B13: 523940 : Portfolio Management and Investment Advice
A15: Fax | B15: Closing Stock Price
A16: 650 312-3655 | B16: 20.11 (as of 12/30/2024)
A18: Number of Employees | B18: Incorporated
A19: 9,200 (Approximate Full-Time as of 09/30/2023) | B19: December 1969 , DE, United States
A21: Country | B21: Mergent Dividend Achiever
A22: United States | B22: Yes, # of Years: 34
A24: Exchange and Ticker | B24: Number of Shareholders
A25: NYS : BEN | B25: 2,476 (record) (as of 10/31/2023)
A27: Primary SIC
A28: 6282 : Investment advice
A31: Business Summary
A32: Franklin Resources, Inc. is a global investment management company with subsidiaries operating as Franklin Templeton and serving clients in over 150 countries. It offers specialization on a global scale, bringing capabilities in fixed income, equity,
A33: alternatives and multi-asset solutions. Co. provides its investment management and related services to retail, institutional and high-net-worth investors in jurisdictions worldwide. Its investment products include sponsored funds, as well as
A34: institutional and high-net-worth separate accounts, retail separately managed account programs, sub-advised products, and other investment vehicles.
A36: * all results are stated in US Dollars
A38: Peer Grouping by: | B38: SIC
A39: Peer Scope: | B39: worldwide
A41: Company Name | B41: Current Ratio - latest | D41: Quick Ratio - latest | F41: Total Debt to Equity - latest | H41: Inventory Turnover - latest | J41: Operating Margin % - latest | L41: ROA % (Net) - latest | N41: ROI % (Operating) - latest | P41: ROE % (Net) - latest | R41: Total Asset Turnover - latest | T41: Net Profit Margin % - latest | V41: Interest Coverage - latest

Sheet mergent_work
A2: Target Country (United States)
A3: Peer Grouping by: | B3: SIC
A4: Peer Scope: | B4: country
A6: Company Name | B6: Current Ratio - latest | D6: Quick Ratio - latest | F6: Total Debt to Equity - latest | H6: Inventory Turnover - latest | J6: Operating Margin % - latest | L6: ROA % (Net) - latest | N6: ROI % (Operating) - latest | P6: ROE % (Net) - latest | R6: Total Asset Turnover - latest | T6: Net Profit Margin % - latest | V6: Interest Coverage - latest
A20: 25th percentile | B20: =_xlfn.PERCENTILE.INC(B7:B15,0.25) -> #NUM! | D20: =_xlfn.PERCENTILE.INC(D7:D15,0.25) -> #NUM! | F20: =_xlfn.PERCENTILE.INC(F7:F15,0.25) -> #NUM! | H20: =_xlfn.PERCENTILE.INC(H7:H15,0.25) -> #NUM! | J20: =_xlfn.PERCENTILE.INC(J7:J15,0.25) -> #NUM! | L20: =_xlfn.PERCENTILE.INC(L7:L15,0.25) -> #NUM! | N20: =_xlfn.PERCENTILE.INC(N7:N15,0.25) -> #NUM! | P20: =_xlfn.PERCENTILE.INC(P7:P15,0.25) -> #NUM! | R20: =_xlfn.PERCENTILE.INC(R7:R15,0.25) -> #NUM! | T20: =_xlfn.PERCENTILE.INC(T7:T15,0.25) -> #NUM! | V20: =_xlfn.PERCENTILE.INC(V7:V15,0.25) -> #NUM!
A21: Median | B21: =MEDIAN(B7:B15) -> #NUM! | D21: =MEDIAN(D7:D15) -> #NUM! | F21: =MEDIAN(F7:F15) -> #NUM! | H21: =MEDIAN(H7:H15) -> #NUM! | J21: =MEDIAN(J7:J15) -> #NUM! | L21: =MEDIAN(L7:L15) -> #NUM! | N21: =MEDIAN(N7:N15) -> #NUM! | P21: =MEDIAN(P7:P15) -> #NUM! | R21: =MEDIAN(R7:R15) -> #NUM! | T21: =MEDIAN(T7:T15) -> #NUM! | V21: =MEDIAN(V7:V15) -> #NUM!
A22: Mean | B22: =AVERAGE(B7:B15) -> #DIV/0! | D22: =AVERAGE(D7:D15) -> #DIV/0! | F22: =AVERAGE(F7:F15) -> #DIV/0! | H22: =AVERAGE(H7:H15) -> #DIV/0! | J22: =AVERAGE(J7:J15) -> #DIV/0! | L22: =AVERAGE(L7:L15) -> #DIV/0! | N22: =AVERAGE(N7:N15) -> #DIV/0! | P22: =AVERAGE(P7:P15) -> #DIV/0! | R22: =AVERAGE(R7:R15) -> #DIV/0! | T22: =AVERAGE(T7:T15) -> #DIV/0! | V22: =AVERAGE(V7:V15) -> #DIV/0!
A23: 75th percentile | B23: =_xlfn.PERCENTILE.INC(B7:B15,0.75) -> #NUM! | D23: =_xlfn.PERCENTILE.INC(D7:D15,0.75) -> #NUM! | F23: =_xlfn.PERCENTILE.INC(F7:F15,0.75) -> #NUM! | H23: =_xlfn.PERCENTILE.INC(H7:H15,0.75) -> #NUM! | J23: =_xlfn.PERCENTILE.INC(J7:J15,0.75) -> #NUM! | L23: =_xlfn.PERCENTILE.INC(L7:L15,0.75) -> #NUM! | N23: =_xlfn.PERCENTILE.INC(N7:N15,0.75) -> #NUM! | P23: =_xlfn.PERCENTILE.INC(P7:P15,0.75) -> #NUM! | R23: =_xlfn.PERCENTILE.INC(R7:R15,0.75) -> #NUM! | T23: =_xlfn.PERCENTILE.INC(T7:T15,0.75) -> #NUM! | V23: =_xlfn.PERCENTILE.INC(V7:V15,0.75) -> #NUM!

Sheet mergent_report
C1: Financial statement analysis for firm: comparison with peers, most recent data
A2: Mergent variable | B2: Our variable | C2: My company | D2: Peer median
A3: Current Ratio - latest | B3: Current ratio | C3: =mergent_work!B18 -> 0 | D3: =mergent_work!B21 -> #NUM!
A4: Quick Ratio - latest | B4: Quick ratio | C4: =mergent_work!D18 -> 0 | D4: =mergent_work!D21 -> #NUM!
A5: Interest Coverage - latest | B5: Times interest earned (from EBIT) | C5: =mergent_work!V18 -> 0 | D5: =mergent_work!V21 -> #NUM!
A6: Total Debt to Equity - latest | B6: Debt-to-equity | C6: =mergent_work!F18 -> 0 | D6: =mergent_work!F21 -> #NUM!
A7: Inventory Turnover - latest | B7: Inventory turnover | C7: =mergent_work!H18 -> 0 | D7: =mergent_work!H21 -> #NUM!
A8: Total Asset Turnover - latest | B8: Asset turnover | C8: =mergent_work!R18 -> 0 | D8: =mergent_work!R21 -> #NUM!
A9: Operating Margin % - latest | B9: Operating profit margin | C9: =mergent_work!J18 -> 0 | D9: =mergent_work!J21 -> #NUM!
A10: Net Profit Margin % - latest | B10: Net profit margin | C10: =mergent_work!T18 -> 0 | D10: =mergent_work!T21 -> #NUM!
A11: ROA % (Net) - latest | B11: Return on assets | C11: =mergent_work!L18 -> 0 | D11: =mergent_work!L21 -> #NUM!
A12: ROI % (Operating) - latest | B12: Return on invested capital | C12: =mergent_work!N18 -> 0 | D12: =mergent_work!N21 -> #NUM!

Sheet WACC
A1: Market value of equity | E1: If the interest coverage ratio (based on EBIT) is
A2: Weighted average basic shares outstanding (in millions, end of historical period) | B2: =fin_model!H54 -> 0 | E2: Greater than | F2: And equal to or less than | G2: Then rating is | H2: And spread is
A3: Price (as of valuation date) | B3: =fin_model!C5 -> 0 | E3: 8.5 | F3: Infinity | G3: Aaa / AAA | H3: 0.0059
A4: Market value of equity ($ millions) | B4: =WACC!B2*WACC!B3 -> 0 | E4: 6.5 | F4: 8.5 | G4: Aa2 / AA | H4: 0.007
E5: 5.5 | F5: 6.5 | G5: A1 / A+ | H5: 0.0092
A6: Market value of debt | E6: 4.25 | F6: 5.5 | G6: A2 / A | H6: 0.0107
A7: Short-term debt (at end of historical period) | B7: =fin_model!H41 -> 0 | E7: 3 | F7: 4.25 | G7: A3 / A- | H7: 0.0121
A8: Current portion of long-term debt (at end of historical period) | B8: =fin_model!H42 -> 0 | E8: 2.5 | F8: 3 | G8: Baa2 / BBB | H8: 0.0147
A9: Long-term debt in long-term liabilities (at end of historical period) | B9: =fin_model!H45 -> 0 | E9: 2.25 | F9: 2.5 | G9: Ba1 / BB+ | H9: 0.0174
A10: Market value of debt ($ millions) | B10: =SUM(B7:B9) -> 0 | E10: 2 | F10: 2.25 | G10: Ba2 / BB | H10: 0.0221
E11: 1.75 | F11: 2 | G11: B1 / B+ | H11: 0.0314
A12: Market value of debt & equity | E12: 1.5 | F12: 1.75 | G12: B2 / B | H12: 0.0361
A13: Market value of debt & equity ($ millions) | B13: =B4+B10 -> 0 | E13: 1.25 | F13: 1.5 | G13: B3 / B- | H13: 0.0524
E14: 0.8 | F14: 1.25 | G14: Caa / CCC | H14: 0.0851
A15: Weights | E15: 0.65 | F15: 0.8 | G15: Ca2 / CC | H15: 0.1178
A16: Equity weight | B16: =B4/B13 -> #DIV/0! | E16: 0.2 | F16: 0.65 | G16: C2 / C | H16: 0.17
A17: Debt weight | B17: =B10/B13 -> #DIV/0! | E17: Negative infinity | F17: 0.2 | G17: D2 / D | H17: 0.2
E18: Source of table
A19: Tax rate
A20: Tax rate (rounded to 2 decimal places) | B20: 0.225 | C20: Average tax rate from 2019 - 2022
P21: Value of debt may be different from balance sheet to represent difference between carrying value and fair value
A22: Expected return of debt
A23: EBIT in last year of historical period | B23: =fin_model!H19-fin_model!H16 -> 0
A24: Interest expense from debt in last year of historical period (as positive) | B24: =-fin_model!H16 -> 0 | R24: Sums of weighted interest and $ amount | S24: =SUM(S27:S65) -> 2788.9 | T24: =SUM(T27:T65) -> 69.98532
A25: Times interest earned = EBIT/interest | B25: =B23/B24 -> #DIV/0! | R25: Weighted int / $ amount | S25: =(T24/S24) -> 0.025094238
A26: Spread (according to times interest earned, external rating, or analyst judgement) | B26: 0.0059 | P26: Year debt is due | R26: Interest rate | S26: $ amount owed | T26: Weighted Interest
A27: Risk-free rate | B27: 0.0457 | C27: 10 year treasury bond return (10 year is standard per Corporate finance Investment and Advisory Application) | P27: 2024 | T27: =R27*S27 -> 0
A28: Expected return of firm's debt (not rounded) | B28: =B27+B26 -> 0.0516 | C28: if company is private B29 = B28, if company is public B29 = C29 | P28: =P27+1 -> 2025 | R28: 0.0297 | S28: 400 | T28: =R28*S28 -> 11.88
A29: Expected return of firm's debt (rounded) | B29: =ROUND(C29,4) -> 0.0251 | C29: =S25 -> 0.025094238 | P29: =P28+1 -> 2026 | R29: 0.018 | S29: 469.5 | T29: =R29*S29 -> 8.451
D30: 2nd method return on debt | P30: =P29+1 -> 2027 | T30: =R30*S30 -> 0
A31: Expected return of equity = RF + (β × market premium) | P31: =P30+1 -> 2028 | T31: =R31*S31 -> 0
A32: Risk-free rate | B32: =B27 -> 0.0457 | P32: =P31+1 -> 2029 | T32: =R32*S32 -> 0
A33: Beta | B33: 1.57 | C33: (3 year monthly) | P33: =P32+1 -> 2030 | R33: 0.0174 | S33: 847.5 | T33: =R33*S33 -> 14.7465
A34: Market premium | B34: 0.05 | C34: Kroll | P34: =P33+1 -> 2031 | T34: =R34*S34 -> 0
A35: Expected return of firm's equity (not rounded) | B35: =B32+(B33*B34) -> 0.1242 | P35: =P34+1 -> 2032 | T35: =R35*S35 -> 0
A36: Expected return of firm's equity (rounded) | B36: =ROUND(B35,4) -> 0.1242 | P36: =P35+1 -> 2033 | T36: =R36*S36 -> 0
P37: =P36+1 -> 2034 | T37: =R37*S37 -> 0
A38: WACC = [(E/V) × RE] + [(D/V) × (1 – Tc) × RD] | P38: =P37+1 -> 2035 | T38: =R38*S38 -> 0
A39: Equity weight | B39: =B16 -> #DIV/0! | P39: =P38+1 -> 2036 | T39: =R39*S39 -> 0
A40: Expected return of firm's equity (rounded) | B40: =B36 -> 0.1242 | P40: =P39+1 -> 2037 | T40: =R40*S40 -> 0
A41: Debt weight | B41: =B17 -> #DIV/0! | P41: =P40+1 -> 2038 | T41: =R41*S41 -> 0
A42: 1 - tax rate | B42: =1-B20 -> 0.775 | P42: =P41+1 -> 2039 | T42: =R42*S42 -> 0
A43: Expected return of firm's debt (rounded) | B43: =B29 -> 0.0251 | P43: =P42+1 -> 2040 | T43: =R43*S43 -> 0
A44: WACC (not rounded) | B44: =((B4/B13)*B36)+((B10/B13)*(1-B20)*B29) -> #DIV/0! | P44: =P43+1 -> 2041 | T44: =R44*S44 -> 0
A45: WACC (rounded) | B45: =ROUND(B44,4) -> #DIV/0! | C45: <1 | P45: =P44+1 -> 2042 | T45: =R45*S45 -> 0
P46: =P45+1 -> 2043 | T46: =R46*S46 -> 0
P47: =P46+1 -> 2044 | R47: 0.0338 | S47: 723.9 | T47: =R47*S47 -> 24.46782
P48: =P47+1 -> 2045 | T48: =R48*S48 -> 0
P49: =P48+1 -> 2046 | T49: =R49*S49 -> 0
P50: =P49+1 -> 2047 | T50: =R50*S50 -> 0
P51: =P50+1 -> 2048 | T51: =R51*S51 -> 0
P52: =P51+1 -> 2049 | T52: =R52*S52 -> 0
A53: =A1 -> Market value of equity | P53: =P52+1 -> 2050 | T53: =R53*S53 -> 0
A54: =A2 -> Weighted average basic shares outstanding (in millions, end of historical period) | B54: =B2 -> 0 | P54: =P53+1 -> 2051 | R54: 0.03 | S54: 348 | T54: =R54*S54 -> 10.44
A55: =A3 -> Price (as of valuation date) | B55: =B3 -> 0 | P55: =P54+1 -> 2052 | T55: =R55*S55 -> 0
A56: =A4 -> Market value of equity ($ millions) | B56: =B4 -> 0 | P56: =P55+1 -> 2053 | T56: =R56*S56 -> 0
A57: =A6 -> Market value of debt | P57: =P56+1 -> 2054 | T57: =R57*S57 -> 0
A58: =A7 -> Short-term debt (at end of historical period) | B58: =B7 -> 0 | P58: =P57+1 -> 2055 | T58: =R58*S58 -> 0
A59: =A8 -> Current portion of long-term debt (at end of historical period) | B59: =B8 -> 0 | P59: =P58+1 -> 2056 | T59: =R59*S59 -> 0
A60: =A9 -> Long-term debt in long-term liabilities (at end of historical period) | B60: =B9 -> 0 | P60: =P59+1 -> 2057 | T60: =R60*S60 -> 0
A61: =A10 -> Market value of debt ($ millions) | B61: =B10 -> 0 | P61: =P60+1 -> 2058 | T61: =R61*S61 -> 0
A62: =A12 -> Market value of debt & equity | L62: Weighted Interest | P62: =P61+1 -> 2059 | T62: =R62*S62 -> 0
A63: =A13 -> Market value of debt & equity ($ millions) | B63: =B13 -> 0 | L63: =T28 -> 11.88 | P63: =P62+1 -> 2060 | T63: =R63*S63 -> 0
A64: =A15 -> Weights | L64: =T29 -> 8.451 | P64: =P63+1 -> 2061 | T64: =R64*S64 -> 0
A65: =A16 -> Equity weight | B65: =B16 -> #DIV/0! | L65: =T33 -> 14.7465 | P65: =P64+1 -> 2062 | T65: =R65*S65 -> 0
A66: =A17 -> Debt weight | B66: =B17 -> #DIV/0! | L66: =T47 -> 24.46782
A67: =A22 -> Expected return of debt | L67: =T54 -> 10.44
A68: =R24 -> Sums of weighted interest and $ amount | B68: =S24 -> 2788.9 | C68: =T24 -> 69.98532
A69: =R25 -> Weighted int / $ amount | B69: =S25 -> 0.025094238 | C69: =T25 -> 0
A75: =A19 -> Tax rate
A76: =A20 -> Tax rate (rounded to 2 decimal places) | B76: =B20 -> 0.225
A79: Expected Return on Equity
A80: =A32 -> Risk-free rate | B80: =B32 -> 0.0457
A81: =A33 -> Beta | B81: =B33 -> 1.57
A82: =A34 -> Market premium | B82: =B34 -> 0.05
A83: Expected return of firms equity | B83: =B35 -> 0.1242
A84: =A36 -> Expected return of firm's equity (rounded) | B84: =B36 -> 0.1242
A85: WACC
A86: =A39 -> Equity weight | B86: =B39 -> #DIV/0!
A87: Expected return of firms equity | B87: =B40 -> 0.1242
A88: =A41 -> Debt weight | B88: =B41 -> #DIV/0!
A89: Tax rate | B89: =1-B42 -> 0.225
A90: Expected return of firms debt | B90: =B43 -> 0.0251
A91: WACC | B91: =B44 -> #DIV/0!

Sheet DCF_-_FCFF_341
B1: DCF Analysis | C1: Forecast yr 1 | D1: Forecast yr 2 | E1: Forecast yr 3 | F1: Forecast yr 4 | G1: Forecast yr 5 | H1: Forecast yr 6 | I1: Terminal
B2: FCFF & Terminal Value
B3: EBIT × (1 - tax rate) | C3: =(fin_model!I19-fin_model!I16)*(1-WACC!$B20) -> #DIV/0! | D3: =(fin_model!J19-fin_model!J16)*(1-WACC!$B20) -> #DIV/0! | E3: =(fin_model!K19-fin_model!K16)*(1-WACC!$B20) -> #DIV/0! | F3: =(fin_model!L19-fin_model!L16)*(1-WACC!$B20) -> #DIV/0! | G3: =(fin_model!M19-fin_model!M16)*(1-WACC!$B20) -> #DIV/0! | H3: =(fin_model!N19-fin_model!N16)*(1-WACC!$B20) -> #DIV/0!
B4: Depreciation | C4: =fin_model!I60 -> #DIV/0! | D4: =fin_model!J60 -> #DIV/0! | E4: =fin_model!K60 -> #DIV/0! | F4: =fin_model!L60 -> #DIV/0! | G4: =fin_model!M60 -> #DIV/0! | H4: =fin_model!N60 -> #DIV/0!
B5: Amortization | C5: =fin_model!I61 -> #DIV/0! | D5: =fin_model!J61 -> #DIV/0! | E5: =fin_model!K61 -> #DIV/0! | F5: =fin_model!L61 -> #DIV/0! | G5: =fin_model!M61 -> #DIV/0! | H5: =fin_model!N61 -> #DIV/0!
B6: Other cash flow from operating activities | C6: =fin_model!I62 -> #DIV/0! | D6: =fin_model!J62 -> #DIV/0! | E6: =fin_model!K62 -> #DIV/0! | F6: =fin_model!L62 -> #DIV/0! | G6: =fin_model!M62 -> #DIV/0! | H6: =fin_model!N62 -> #DIV/0!
B7: Capital expenditures (CAPEX) | C7: =fin_model!I66 -> #DIV/0! | D7: =fin_model!J66 -> #DIV/0! | E7: =fin_model!K66 -> #DIV/0! | F7: =fin_model!L66 -> #DIV/0! | G7: =fin_model!M66 -> #DIV/0! | H7: =fin_model!N66 -> #DIV/0!
B8: FCFF | C8: =SUM(C3:C7) -> #DIV/0! | D8: =SUM(D3:D7) -> #DIV/0! | E8: =SUM(E3:E7) -> #DIV/0! | F8: =SUM(F3:F7) -> #DIV/0! | G8: =SUM(G3:G7) -> #DIV/0! | H8: =SUM(H3:H7) -> #DIV/0!
B9: Terminal value (as a perpetuity) | I9: =D53 -> #DIV/0!
B10: Terminal value (from a multiple) | I10: =C61 -> #DIV/0!
B12: Terminal value (as a perpetuity)
B13: Years to discount | C13: 1 | D13: 2 | E13: 3 | F13: 4 | G13: 5 | H13: 6 | I13: 6
B14: Present values with terminal value as a perpetuity | C14: =C8/(1+$C$22)^(C13) -> #DIV/0! | D14: =D8/(1+$C$22)^D13 -> #DIV/0! | E14: =E8/(1+$C$22)^E13 -> #DIV/0! | F14: =F8/(1+$C$22)^F13 -> #DIV/0! | G14: =G8/(1+$C$22)^G13 -> #DIV/0! | H14: =H8/(1+$C$22)^H13 -> #DIV/0! | I14: =I9/(1+C22)^I13 -> #DIV/0!
B16: Terminal value (from a multiple)
B17: Years to discount | C17: 1 | D17: 2 | E17: 3 | F17: 4 | G17: 5 | H17: 6 | I17: 6
B18: Present values with terminal value from a multiple | C18: =C8/(1+$C$22)^(C13) -> #DIV/0! | D18: =D8/(1+$C$22)^D13 -> #DIV/0! | E18: =E8/(1+$C$22)^E13 -> #DIV/0! | F18: =F8/(1+$C$22)^F13 -> #DIV/0! | G18: =G8/(1+$C$22)^G13 -> #DIV/0! | H18: =H8/(1+$C$22)^H13 -> #DIV/0! | I18: =I10/(1+C22)^I17 -> #DIV/0!
B20: Valuation Analysis
B21: Terminal growth rate | C21: 0.01
B22: WACC | C22: =WACC!B45 -> #DIV/0!
B23: Expected return of equity | C23: =WACC!B36 -> 0.1242
B24: Terminal EV/EBITDA | C24: 8 | E24: Sourced from Damodaran | F24: If no data from damodaran use equidam
B26: Date of end of historical period | C26: =fin_model!C7 -> 0
B27: Valuation date | C27: =fin_model!C6 -> 0
B29: Terminal value (as a perpetuity)
B30: Estimated enterprise value (at end of historical period) | C30: =SUM(C14:I14) -> #DIV/0!
B31: Value of net debt (at end of historical period) | C31: =C67 -> 0
B32: Estimated equity value (at end of historical period) | C32: =C30-C31 -> #DIV/0!
B33: Weighted average basic shares outstanding (in millions, end of historical period) | C33: =fin_model!H54 -> 0
B34: Estimated price per share (at end of historical period) | C34: =C32/C33 -> #DIV/0!
B35: Share of year between end of historical period & valuation date | C35: =YEARFRAC(C27,C26) -> 0
B36: Estimated price per share (at valuation date) | C36: =C34*(1+C23)^C35 -> #DIV/0!
B38: Terminal value (from a multiple)
B39: Estimated enterprise value (at end of historical period) | C39: =SUM(C18:I18) -> #DIV/0!
B40: Value of net debt (at end of historical period) | C40: =C31 -> 0
B41: Estimated equity value (at end of historical period) | C41: =C39-C40 -> #DIV/0!
B42: Weighted average basic shares outstanding (in millions, end of historical period) | C42: =C33 -> 0
B43: Estimated price per share (at end of historical period) | C43: =C41/C42 -> #DIV/0!
B44: Share of year between end of historical period & valuation date | C44: =C35 -> 0
B45: Estimated price per share (at valuation date) | C45: =C43*(1+C23)^C44 -> #DIV/0!
C48: Forecast yr 6
B49: FCFF | C49: =H8 -> #DIV/0!
B50: 1+g | C50: =1+C21 -> 1.01
B51: FCFF(N+1) | D51: =C49*C50 -> #DIV/0!
B52: WACC-g | D52: =C22-C21 -> #DIV/0!
B53: FTV (Perp) = FFCFF(N+1)/WACC-g | D53: =D51/D52 -> #DIV/0!
B56: EBIT(N) | C56: =fin_model!N15 -> #DIV/0!
B57: D(N) | C57: =H4 -> #DIV/0!
B58: A(N) | C58: =H5 -> #DIV/0!
B59: EBITDA(N) | C59: =SUM(C56:C58) -> #DIV/0!
B60: exit multiple | C60: =C24 -> 8
B61: TV | C61: =C59*C60 -> #DIV/0!
B63: ST debt | C63: =fin_model!G41 -> 0
B64: Current portion | C64: =fin_model!G42 -> 0
B65: LT debt | C65: =fin_model!G45 -> 0
B66: cash | C66: =fin_model!G28 -> 0
B67: net debt | C67: =SUM(C63:C65)-C66 -> 0
B70: EV as of valuation date (Price at valuation date * shares outstanding + net debt) | C70: =fin_model!C5*fin_model!G54+'DCF_-_FCFF_341'!C67 -> 0

Sheet DCF_-_FCFF_timing
B1: DCF Analysis | C1: Forecast yr 1 | D1: Forecast yr 2 | E1: Forecast yr 3 | F1: Forecast yr 4 | G1: Forecast yr 5 | H1: Forecast yr 6 | I1: Terminal
B2: FCFF & Terminal Value
B3: EBIT × (1 - tax rate) | C3: ='DCF_-_FCFF_341'!C3 -> #DIV/0! | D3: ='DCF_-_FCFF_341'!D3 -> #DIV/0! | E3: ='DCF_-_FCFF_341'!E3 -> #DIV/0! | F3: ='DCF_-_FCFF_341'!F3 -> #DIV/0! | G3: ='DCF_-_FCFF_341'!G3 -> #DIV/0! | H3: ='DCF_-_FCFF_341'!H3 -> #DIV/0!
B4: Depreciation | C4: ='DCF_-_FCFF_341'!C4 -> #DIV/0! | D4: ='DCF_-_FCFF_341'!D4 -> #DIV/0! | E4: ='DCF_-_FCFF_341'!E4 -> #DIV/0! | F4: ='DCF_-_FCFF_341'!F4 -> #DIV/0! | G4: ='DCF_-_FCFF_341'!G4 -> #DIV/0! | H4: ='DCF_-_FCFF_341'!H4 -> #DIV/0!
B5: Amortization | C5: ='DCF_-_FCFF_341'!C5 -> #DIV/0! | D5: ='DCF_-_FCFF_341'!D5 -> #DIV/0! | E5: ='DCF_-_FCFF_341'!E5 -> #DIV/0! | F5: ='DCF_-_FCFF_341'!F5 -> #DIV/0! | G5: ='DCF_-_FCFF_341'!G5 -> #DIV/0! | H5: ='DCF_-_FCFF_341'!H5 -> #DIV/0!
B6: Other cash flow from operating activities | C6: ='DCF_-_FCFF_341'!C6 -> #DIV/0! | D6: ='DCF_-_FCFF_341'!D6 -> #DIV/0! | E6: ='DCF_-_FCFF_341'!E6 -> #DIV/0! | F6: ='DCF_-_FCFF_341'!F6 -> #DIV/0! | G6: ='DCF_-_FCFF_341'!G6 -> #DIV/0! | H6: ='DCF_-_FCFF_341'!H6 -> #DIV/0!
B7: Capital expenditures (CAPEX) | C7: ='DCF_-_FCFF_341'!C7 -> #DIV/0! | D7: ='DCF_-_FCFF_341'!D7 -> #DIV/0! | E7: ='DCF_-_FCFF_341'!E7 -> #DIV/0! | F7: ='DCF_-_FCFF_341'!F7 -> #DIV/0! | G7: ='DCF_-_FCFF_341'!G7 -> #DIV/0! | H7: ='DCF_-_FCFF_341'!H7 -> #DIV/0!
B8: FCFF | C8: =SUM(C3:C7) -> #DIV/0! | D8: =SUM(D3:D7) -> #DIV/0! | E8: =SUM(E3:E7) -> #DIV/0! | F8: =SUM(F3:F7) -> #DIV/0! | G8: =SUM(G3:G7) -> #DIV/0! | H8: =SUM(H3:H7) -> #DIV/0!
B9: Terminal value (as a perpetuity) | I9: =D55 -> #DIV/0!
B10: Terminal value (from a multiple) | I10: =C63 -> #DIV/0!
B12: Share of year expected for CF or TV | C12: =1-YEARFRAC(fin_model!C7,fin_model!C6) -> 1 | D12: 1 | E12: 1 | F12: 1 | G12: 1 | H12: 1 | I12: 1
B13: Expected FCFF or TV (as a perpetuity) | C13: =C8*C12 -> #DIV/0! | D13: =D8*D12 -> #DIV/0! | E13: =E8*E12 -> #DIV/0! | F13: =F8*F12 -> #DIV/0! | G13: =G8*G12 -> #DIV/0! | H13: =H8*H12 -> #DIV/0! | I13: =I9*I12 -> #DIV/0!
B14: Expected FCFF or TV (from a multiple) | C14: =C8*C12 -> #DIV/0! | D14: =D8*D12 -> #DIV/0! | E14: =E8*E12 -> #DIV/0! | F14: =F8*F12 -> #DIV/0! | G14: =G8*G12 -> #DIV/0! | H14: =H8*H12 -> #DIV/0! | I14: =I10*I12 -> #DIV/0!
B16: Terminal value (as a perpetuity)
B17: Period | C17: 1 | D17: 2 | E17: 3 | F17: 4 | G17: 5 | H17: 6 | I17: 6
B18: Years to discount | C18: =0.5*(1-YEARFRAC(C31,C32)) -> 0.5 | D18: =D17-YEARFRAC($C$31,$C32)-0.5 -> 1.5 | E18: =E17-YEARFRAC($C$31,$C32)-0.5 -> 2.5 | F18: =F17-YEARFRAC($C$31,$C32)-0.5 -> 3.5 | G18: =G17-YEARFRAC($C$31,$C32)-0.5 -> 4.5 | H18: =H17-YEARFRAC($C$31,$C32)-0.5 -> 5.5 | I18: =I17-YEARFRAC($C$31,$C32)-0.5 -> 5.5
B19: Present values with terminal value as a perpetuity | C19: =C13/(1+$C$28)^C18 -> #DIV/0! | D19: =D13/(1+$C$28)^D18 -> #DIV/0! | E19: =E13/(1+$C$28)^E18 -> #DIV/0! | F19: =F13/(1+$C$28)^F18 -> #DIV/0! | G19: =G13/(1+$C$28)^G18 -> #DIV/0! | H19: =H13/(1+$C$28)^H18 -> #DIV/0! | I19: =I13/(1+$C$28)^I18 -> #DIV/0!
B21: Terminal value (from a multiple)
B22: Period | C22: 1 | D22: 2 | E22: 3 | F22: 4 | G22: 5 | H22: 6 | I22: 6
B23: Years to discount | C23: =C18 -> 0.5 | D23: =D18 -> 1.5 | E23: =E18 -> 2.5 | F23: =F18 -> 3.5 | G23: =G18 -> 4.5 | H23: =H18 -> 5.5 | I23: =I17-YEARFRAC($C$31,$C32) -> 6
B24: Present values with terminal value from a multiple | C24: =C14/(1+$C$28)^C18 -> #DIV/0! | D24: =D14/(1+$C$28)^D18 -> #DIV/0! | E24: =E14/(1+$C$28)^E18 -> #DIV/0! | F24: =F14/(1+$C$28)^F18 -> #DIV/0! | G24: =G14/(1+$C$28)^G18 -> #DIV/0! | H24: =H14/(1+$C$28)^H18 -> #DIV/0! | I24: =I14/(1+$C$28)^I23 -> #DIV/0!
B26: Valuation Analysis
B27: Terminal growth rate | C27: ='DCF_-_FCFF_341'!C21 -> 0.01 | J27: What-If Analysis of DCF as a perpetuity
B28: WACC | C28: ='DCF_-_FCFF_341'!C22 -> #DIV/0! | L28: Terminal Growth Rate
B29: Terminal EV/EBITDA | C29: ='DCF_-_FCFF_341'!C24 -> 8 | I29: =C41 -> #DIV/0! | J29: 0.005 | K29: 0.0075 | L29: 0.01 | M29: 0.0125 | N29: 0.015
I30: 0.1025 | J30: #DIV/0! | K30: #DIV/0! | L30: #DIV/0! | M30: #DIV/0! | N30: #DIV/0!
B31: Date of end of historical period | C31: =fin_model!C7 -> 0 | I31: 0.1051 | J31: #DIV/0! | K31: #DIV/0! | L31: #DIV/0! | M31: #DIV/0! | N31: #DIV/0!
B32: Valuation date | C32: ='DCF_-_FCFF_341'!C27 -> 0 | H32: WACC | I32: 0.1076 | J32: #DIV/0! | K32: #DIV/0! | L32: #DIV/0! | M32: #DIV/0! | N32: #DIV/0!
I33: 0.1101 | J33: #DIV/0! | K33: #DIV/0! | L33: #DIV/0! | M33: #DIV/0! | N33: #DIV/0!
I34: 0.1126 | J34: #DIV/0! | K34: #DIV/0! | L34: #DIV/0! | M34: #DIV/0! | N34: #DIV/0!
B36: Terminal value (as a perpetuity) | I36: Price at valuation date | K36: =fin_model!C5 -> 0
B37: Estimated enterprise value (as of valuation date) | C37: =SUM(C19:I19) -> #DIV/0!
B38: Value of net debt (at end of historical period) | C38: ='DCF_-_FCFF_341'!C31 -> 0
B39: Estimated equity value (as of valuation date) | C39: =C37-C38 -> #DIV/0!
B40: Weighted average basic shares outstanding (in millions, end of historical period) | C40: ='DCF_-_FCFF_341'!C33 -> 0
B41: Estimated price per share (as of valuation date) | C41: =C39/C40 -> #DIV/0! | J41: What-If Analysis of DCF as a multiple
L42: Exit Multiple
B43: Terminal value (from a multiple) | I43: =C48 -> #DIV/0! | J43: 8.5 | K43: 9 | L43: 9.5 | M43: 10 | N43: 10.5
B44: Estimated enterprise value (as of valuation date) | C44: =SUM(C24:I24) -> #DIV/0! | I44: 0.1003 | J44: #DIV/0! | K44: #DIV/0! | L44: #DIV/0! | M44: #DIV/0! | N44: #DIV/0!
B45: Value of net debt (at end of historical period) | C45: ='DCF_-_FCFF_341'!C40 -> 0 | I45: 0.1028 | J45: #DIV/0! | K45: #DIV/0! | L45: #DIV/0! | M45: #DIV/0! | N45: #DIV/0!
B46: Estimated equity value (as of valuation date) | C46: =C44-C45 -> #DIV/0! | H46: WACC | I46: 0.1053 | J46: #DIV/0! | K46: #DIV/0! | L46: #DIV/0! | M46: #DIV/0! | N46: #DIV/0!
B47: Weighted average basic shares outstanding (in millions, end of historical period) | C47: ='DCF_-_FCFF_341'!C42 -> 0 | I47: 0.1078 | J47: #DIV/0! | K47: #DIV/0! | L47: #DIV/0! | M47: #DIV/0! | N47: #DIV/0!
B48: Estimated price per share (as of valuation date) | C48: =C46/C47 -> #DIV/0! | I48: 0.1103 | J48: #DIV/0! | K48: #DIV/0! | L48: #DIV/0! | M48: #DIV/0! | N48: #DIV/0!
I49: Price at valuation date | K49: =K36 -> 0
C50: Forecast yr 6
B51: FCFF | C51: =H8 -> #DIV/0!
B52: 1+g | C52: =1+C27 -> 1.01
B53: FCFF(N+1) | D53: =C51*C52 -> #DIV/0!
B54: WACC-g | D54: =C28-C27 -> #DIV/0!
B55: FTV (Perp) = FFCFF(N+1)/WACC-g | D55: =D53/D54 -> #DIV/0!
B58: EBIT(N) | C58: =fin_model!N15 -> #DIV/0!
B59: D(N)
B60: A(N) | C60: =H5 -> #DIV/0!
B61: EBITDA(N) | C61: =SUM(C58:C60) -> #DIV/0!
B62: exit multiple | C62: =C29 -> 8
B63: TV | C63: =C61*C62 -> #DIV/0!
B65: ST debt | C65: =fin_model!G41 -> 0
B66: Current portion | C66: =fin_model!G42 -> 0
B67: LT debt | C67: =fin_model!G45 -> 0
B68: cash | C68: =fin_model!G28 -> 0
B69: net debt | C69: =SUM(C63:C65)-C66 -> #DIV/0!
B72: EV as of valuation date (Price at valuation date * shares outstanding + net debt) | C72: =fin_model!C5*fin_model!G54+'DCF_-_FCFF_341'!C67 -> 0

Sheet DCF_-_FCFF_timing_&_normalized
B1: DCF Analysis | C1: Forecast yr 1 | D1: Forecast yr 2 | E1: Forecast yr 3 | F1: Forecast yr 4 | G1: Forecast yr 5 | H1: Forecast yr 6 | I1: Terminal | J1: Normalized yr 6
B2: FCFF & Terminal Value
B3: EBIT × (1 - tax rate) | C3: ='DCF_-_FCFF_341'!C3 -> #DIV/0! | D3: ='DCF_-_FCFF_341'!D3 -> #DIV/0! | E3: ='DCF_-_FCFF_341'!E3 -> #DIV/0! | F3: ='DCF_-_FCFF_341'!F3 -> #DIV/0! | G3: ='DCF_-_FCFF_341'!G3 -> #DIV/0! | H3: ='DCF_-_FCFF_341'!H3 -> #DIV/0! | J3: =E75 -> #DIV/0!
B4: Depreciation | C4: ='DCF_-_FCFF_341'!C4 -> #DIV/0! | D4: ='DCF_-_FCFF_341'!D4 -> #DIV/0! | E4: ='DCF_-_FCFF_341'!E4 -> #DIV/0! | F4: ='DCF_-_FCFF_341'!F4 -> #DIV/0! | G4: ='DCF_-_FCFF_341'!G4 -> #DIV/0! | H4: ='DCF_-_FCFF_341'!H4 -> #DIV/0! | J4: =H4 -> #DIV/0!
B5: Amortization | C5: ='DCF_-_FCFF_341'!C5 -> #DIV/0! | D5: ='DCF_-_FCFF_341'!D5 -> #DIV/0! | E5: ='DCF_-_FCFF_341'!E5 -> #DIV/0! | F5: ='DCF_-_FCFF_341'!F5 -> #DIV/0! | G5: ='DCF_-_FCFF_341'!G5 -> #DIV/0! | H5: ='DCF_-_FCFF_341'!H5 -> #DIV/0! | J5: =H5 -> #DIV/0!
B6: Other cash flow from operating activities | C6: ='DCF_-_FCFF_341'!C6 -> #DIV/0! | D6: ='DCF_-_FCFF_341'!D6 -> #DIV/0! | E6: ='DCF_-_FCFF_341'!E6 -> #DIV/0! | F6: ='DCF_-_FCFF_341'!F6 -> #DIV/0! | G6: ='DCF_-_FCFF_341'!G6 -> #DIV/0! | H6: ='DCF_-_FCFF_341'!H6 -> #DIV/0! | J6: =H6 -> #DIV/0!
B7: Capital expenditures (CAPEX) | C7: ='DCF_-_FCFF_341'!C7 -> #DIV/0! | D7: ='DCF_-_FCFF_341'!D7 -> #DIV/0! | E7: ='DCF_-_FCFF_341'!E7 -> #DIV/0! | F7: ='DCF_-_FCFF_341'!F7 -> #DIV/0! | G7: ='DCF_-_FCFF_341'!G7 -> #DIV/0! | H7: ='DCF_-_FCFF_341'!H7 -> #DIV/0! | J7: =H7 -> #DIV/0!
B8: FCFF | C8: =SUM(C3:C7) -> #DIV/0! | D8: =SUM(D3:D7) -> #DIV/0! | E8: =SUM(E3:E7) -> #DIV/0! | F8: =SUM(F3:F7) -> #DIV/0! | G8: =SUM(G3:G7) -> #DIV/0! | H8: =SUM(H3:H7) -> #DIV/0! | J8: =SUM(J3:J7) -> #DIV/0!
B9: Terminal value (as a perpetuity) | I9: =F82 -> #DIV/0!
B10: Terminal value (from a multiple) | I10: =E90 -> #DIV/0!
B12: Share of year expected for CF or TV | C12: =1-YEARFRAC(C31,C32) -> 1 | D12: 1 | E12: 1 | F12: 1 | G12: 1 | H12: 1 | I12: 1
B13: Expected FCFF or TV (as a perpetuity) | C13: =C8*C12 -> #DIV/0! | D13: =D8*D12 -> #DIV/0! | E13: =E8*E12 -> #DIV/0! | F13: =F8*F12 -> #DIV/0! | G13: =G8*G12 -> #DIV/0! | H13: =H8*H12 -> #DIV/0! | I13: =I9*I12 -> #DIV/0!
B14: Expected FCFF or TV (from a multiple) | C14: =C8*C12 -> #DIV/0! | D14: =D8*D12 -> #DIV/0! | E14: =E8*E12 -> #DIV/0! | F14: =F8*F12 -> #DIV/0! | G14: =G8*G12 -> #DIV/0! | H14: =H8*H12 -> #DIV/0! | I14: =I10*I12 -> #DIV/0!
B16: Terminal value (as a perpetuity)
B17: Period | C17: 1 | D17: 2 | E17: 3 | F17: 4 | G17: 5 | H17: 6 | I17: 6
B18: Years to discount | C18: =0.5*C12 -> 0.5 | D18: =(D17-1)+$C$12-0.5 -> 1.5 | E18: =(E17-1)+$C$12-0.5 -> 2.5 | F18: =(F17-1)+$C$12-0.5 -> 3.5 | G18: =(G17-1)+$C$12-0.5 -> 4.5 | H18: =(H17-1)+$C$12-0.5 -> 5.5 | I18: =(I17-1)+$C$12-0.5 -> 5.5
B19: Present values with terminal value as a perpetuity | C19: =C13/(1+$C$28)^C18 -> #DIV/0! | D19: =D13/(1+$C$28)^D18 -> #DIV/0! | E19: =E13/(1+$C$28)^E18 -> #DIV/0! | F19: =F13/(1+$C$28)^F18 -> #DIV/0! | G19: =G13/(1+$C$28)^G18 -> #DIV/0! | H19: =H13/(1+$C$28)^H18 -> #DIV/0! | I19: =I13/(1+$C$28)^I18 -> #DIV/0!
B21: Terminal value (from a multiple)
B22: Period | C22: 1 | D22: 2 | E22: 3 | F22: 4 | G22: 5 | H22: 6 | I22: 6
B23: Years to discount | C23: =C18 -> 0.5 | D23: =D18 -> 1.5 | E23: =E18 -> 2.5 | F23: =F18 -> 3.5 | G23: =G18 -> 4.5 | H23: =H18 -> 5.5 | I23: =I18 -> 5.5
B24: Present values with terminal value from a multiple | C24: =C14/(1+$C$28)^C23 -> #DIV/0! | D24: =D14/(1+$C$28)^D23 -> #DIV/0! | E24: =E14/(1+$C$28)^E23 -> #DIV/0! | F24: =F14/(1+$C$28)^F23 -> #DIV/0! | G24: =G14/(1+$C$28)^G23 -> #DIV/0! | H24: =H14/(1+$C$28)^H23 -> #DIV/0! | I24: =I14/(1+$C$28)^I23 -> #DIV/0!
B26: Valuation Analysis
B27: Terminal growth rate | C27: ='DCF_-_FCFF_timing'!C27 -> 0.01
B28: WACC | C28: ='DCF_-_FCFF_timing'!C28 -> #DIV/0!
B29: Terminal EV/EBITDA | C29: ='DCF_-_FCFF_timing'!C29 -> 8
B31: Date of end of historical period | C31: ='DCF_-_FCFF_timing'!C31 -> 0
B32: Valuation date | C32: ='DCF_-_FCFF_timing'!C32 -> 0
B36: Terminal value (as a perpetuity)
B37: Estimated enterprise value (as of valuation date) | C37: =SUM(C19:I19) -> #DIV/0!
B38: Value of net debt (at end of historical period) | C38: ='DCF_-_FCFF_timing'!C38 -> 0
B39: Estimated equity value (as of valuation date) | C39: =C37-C38 -> #DIV/0! | E39: ='DCF_-_FCFF_341'!C36 -> #DIV/0! | F39: =(C41/E39)-1 -> #DIV/0! | G39: 341
B40: Weighted average basic shares outstanding (in millions, end of historical period) | C40: ='DCF_-_FCFF_timing'!C40 -> 0 | E40: ='DCF_-_FCFF_timing'!C41 -> #DIV/0! | F40: =C41/E40-1 -> #DIV/0! | G40: timing
B41: Estimated price per share (as of valuation date) | C41: =C39/C40 -> #DIV/0!
B43: Terminal value (from a multiple)
B44: Estimated enterprise value (as of valuation date) | C44: =SUM(C24:I24) -> #DIV/0! | E44: ='DCF_-_FCFF_341'!C45 -> #DIV/0! | F44: =C48/E44-1 -> #DIV/0! | G44: 341
B45: Value of net debt (at end of historical period) | C45: =C38 -> 0 | E45: ='DCF_-_FCFF_timing'!C48 -> #DIV/0! | F45: =C48/E45-1 -> #DIV/0! | G45: timing
B46: Estimated equity value (as of valuation date) | C46: =C44-C45 -> #DIV/0!
B47: Weighted average basic shares outstanding (in millions, end of historical period) | C47: ='DCF_-_FCFF_timing'!C47 -> 0
B48: Estimated price per share (as of valuation date) | C48: =C46/C47 -> #DIV/0!
B50: Company Name | C50: LTM EBIT | D50: LTM Total Revenue | E50: EBIT/sales | F50: LTM EBITDA
B51: =mkt_comps_summary!A2 -> 0 | C51: =mkt_comps_summary!M2 -> 0 | D51: =mkt_comps_summary!K2 -> 0 | E51: =mkt_comps_summary!M2/D51 -> #DIV/0! | F51: =mkt_comps_summary!L2 -> 0
B52: =mkt_comps_summary!A3 -> 0 | C52: =mkt_comps_summary!M3 -> 0 | D52: =mkt_comps_summary!K3 -> 0 | E52: =mkt_comps_summary!M3/D52 -> #DIV/0! | F52: =mkt_comps_summary!L3 -> 0
B54: =mkt_comps_summary!A5 -> 0 | D54: =mkt_comps_summary!K5 -> 0
B57: =mkt_comps_summary!A8 -> 0 | C57: =mkt_comps_summary!M8 -> 0 | D57: =mkt_comps_summary!K8 -> 0 | E57: =mkt_comps_summary!M8/D57 -> #DIV/0! | F57: =mkt_comps_summary!L8 -> 0
B59: =mkt_comps_summary!A10 -> 0 | D59: =mkt_comps_summary!K10 -> 0
B60: =mkt_comps_summary!A11 -> 0 | C60: =mkt_comps_summary!M11 -> 0 | D60: =mkt_comps_summary!K11 -> 0 | E60: =mkt_comps_summary!M11/D60 -> #DIV/0! | F60: =mkt_comps_summary!L11 -> 0
B63: =mkt_comps_summary!A14 -> 0 | C63: =mkt_comps_summary!M14 -> 0 | D63: =mkt_comps_summary!K14 -> 0 | E63: =mkt_comps_summary!M14/D57 -> #DIV/0! | F63: =mkt_comps_summary!L14 -> 0
B64: *Fill in peer firms above the black cells and firm being valued below the black cells
B65: **Only fill in data for peers that are included in the peer group. If you decide to drop any firms from the original peer group, do not include their data above. Just leave the row blank. If you add any firms to the original peer group, then include them here.
B66: ***LTM EBIT & LTM Total revenue obtained from market comps data
B68: Median peer EBIT/sales | E68: =MEDIAN(E51:E60) -> #DIV/0! | G68: 1-tax rate
B69: Median peer EBIT/sales to firm EBIT/sales | E69: =E68/E63 -> #DIV/0! | G69: =WACC!B42 -> 0.775
E72: Forecast year 6
B73: EBIT * (1-tax rate) | E73: =H3 -> #DIV/0!
B74: Median peer ebit/sales | E74: =E68/E63 -> #DIV/0!
B75: normalized ebit * 1- tax rate | E75: =E73*E74 -> #DIV/0!
B77: TV (Perp) = FCFF (N+1)/(WACC -g) | E77: =J8 -> #DIV/0!
B78: 1+g | E78: =1+C27 -> 1.01
B79: FCFF (N+1) | E79: =E77*E78 -> #DIV/0!
B80: WACC - g | E80: =C28-C27 -> #DIV/0!
B82: TV(Perp) = FCFF(N+1)/WACC - g | F82: =E79/E80 -> #DIV/0!
B85: EBIT | E85: =fin_model!N19-fin_model!N16 -> #DIV/0!
B86: Dep | E86: =fin_model!N60 -> #DIV/0!
B87: Amort | E87: =fin_model!N61 -> #DIV/0!
B88: EBITDA | E88: =SUM(E85:E87) -> #DIV/0!
B89: exit mult | E89: =C29 -> 8
B90: TV | E90: =E88*E89 -> #DIV/0!
D91: Last historic period
B92: short term debt | D92: =fin_model!G41 -> 0
B93: current portion | D93: =fin_model!G42 -> 0
B94: long term debt | D94: =fin_model!G45 -> 0
B95: cash | D95: =fin_model!G81 -> 0
B96: net debt (total debt - cash) | D96: =SUM(D92:D94)-D95 -> 0

Sheet DCF_-_FCFE_341
B1: DCF Analysis | C1: Forecast yr 1 | D1: Forecast yr 2 | E1: Forecast yr 3 | F1: Forecast yr 4 | G1: Forecast yr 5 | H1: Forecast yr 6 | I1: Terminal
B2: FCFE & Terminal Value
B3: Cash flows from operating activities | C3: =fin_model!I63 -> #DIV/0! | D3: =fin_model!J63 -> #DIV/0! | E3: =fin_model!K63 -> #DIV/0! | F3: =fin_model!L63 -> #DIV/0! | G3: =fin_model!M63 -> #DIV/0! | H3: =fin_model!N63 -> #DIV/0!
B4: Capital expenditures (CAPEX) | C4: =fin_model!I66 -> #DIV/0! | D4: =fin_model!J66 -> #DIV/0! | E4: =fin_model!K66 -> #DIV/0! | F4: =fin_model!L66 -> #DIV/0! | G4: =fin_model!M66 -> #DIV/0! | H4: =fin_model!N66 -> #DIV/0!
B5: Net change in debt | C5: =fin_model!I71 -> #DIV/0! | D5: =fin_model!J71 -> #DIV/0! | E5: =fin_model!K71 -> #DIV/0! | F5: =fin_model!L71 -> #DIV/0! | G5: =fin_model!M71 -> #DIV/0! | H5: =fin_model!N71 -> #DIV/0!
B6: FCFE | C6: =C3+C4+C5 -> #DIV/0! | D6: =D3+D4+D5 -> #DIV/0! | E6: =E3+E4+E5 -> #DIV/0! | F6: =F3+F4+F5 -> #DIV/0! | G6: =G3+G4+G5 -> #DIV/0! | H6: =H3+H4+H5 -> #DIV/0!
B7: Terminal value (as a perpetuity) | I7: =C48 -> #DIV/0!
B8: Terminal value (from a multiple) | I8: =C52 -> #DIV/0!
B10: Terminal value (as a perpetuity)
B11: Years to discount | C11: 1 | D11: 2 | E11: 3 | F11: 4 | G11: 5 | H11: 6 | I11: 6
B12: Present values with terminal value as a perpetuity | C12: =C6/(1+$C$21)^C11 -> #DIV/0! | D12: =D6/(1+$C$21)^D11 -> #DIV/0! | E12: =E6/(1+$C$21)^E11 -> #DIV/0! | F12: =F6/(1+$C$21)^F11 -> #DIV/0! | G12: =G6/(1+$C$21)^G11 -> #DIV/0! | H12: =H6/(1+$C$21)^H11 -> #DIV/0! | I12: =I7/(1+C21)^I11 -> #DIV/0!
B14: Terminal value (from a multiple)
B15: Years to discount | C15: =C11 -> 1 | D15: =D11 -> 2 | E15: =E11 -> 3 | F15: =F11 -> 4 | G15: =G11 -> 5 | H15: =H11 -> 6 | I15: =I11 -> 6
B16: Present values with terminal value from a multiple | C16: =C6/(1+$C$21)^C15 -> #DIV/0! | D16: =D6/(1+$C$21)^D15 -> #DIV/0! | E16: =E6/(1+$C$21)^E15 -> #DIV/0! | F16: =F6/(1+$C$21)^F15 -> #DIV/0! | G16: =G6/(1+$C$21)^G15 -> #DIV/0! | H16: =H6/(1+$C$21)^H15 -> #DIV/0! | I16: =I8/(1+C21)^I15 -> #DIV/0!
B18: Valuation Analysis | I18: 1+return on equity ^ yearfrac
B19: Terminal growth rate | C19: ='DCF_-_FCFF_timing_&_normalized'!C27 -> 0.01
B20: WACC | C20: ='DCF_-_FCFF_timing_&_normalized'!C28 -> #DIV/0!
B21: Expected return of equity | C21: =WACC!B36 -> 0.1242
B22: Terminal P/E | C22: 16
B24: Date of end of historical period | C24: ='DCF_-_FCFF_timing_&_normalized'!C31 -> 0
B25: Valuation date | C25: ='DCF_-_FCFF_timing_&_normalized'!C32 -> 0
B27: Terminal value (as a perpetuity)
B28: Estimated equity value (at end of historical period) | C28: =SUM(C12:I12) -> #DIV/0!
B29: Weighted average basic shares outstanding (in millions, end of historical period) | C29: =fin_model!H54 -> 0
B30: Estimated price per share (at end of historical period) | C30: =C28/C29 -> #DIV/0!
B31: Share of year between end of historical period & valuation date | C31: =YEARFRAC(C24,C25) -> 0
B32: Estimated price per share (at valuation date) | C32: =C30*C31 -> #DIV/0!
B34: Terminal value (from a multiple)
B35: Estimated equity value (at end of historical period) | C35: =C28 -> #DIV/0!
B36: Weighted average basic shares outstanding (in millions, end of historical period) | C36: =C29 -> 0
B37: Estimated price per share (at end of historical period) | C37: =SUM(C16:I16)/C36 -> #DIV/0!
B38: Share of year between end of historical period & valuation date | C38: =C31 -> 0
B39: Estimated price per share (at valuation date) | C39: =C37*C38 -> #DIV/0!
B44: FCFE | C44: =H6 -> #DIV/0!
B45: 1+g | C45: =1+C19 -> 1.01
B46: FCFE(N+1) | D46: =C44*C45 -> #DIV/0!
B47: RE-g | D47: =C21-C19 -> 0.1142
B48: TV perp | C48: =D46/D47 -> #DIV/0!
B50: NI | C50: =fin_model!N23 -> #DIV/0!
B51: Exit mult | C51: =C22 -> 16
B52: TV mult | C52: =C50*C51 -> #DIV/0!

Sheet DCF_-_FCFE_timing
B1: DCF Analysis | C1: Forecast yr 1 | D1: Forecast yr 2 | E1: Forecast yr 3 | F1: Forecast yr 4 | G1: Forecast yr 5 | H1: Forecast yr 6 | I1: Terminal
B2: FCFE & Terminal Value
B3: Cash flows from operating activities | C3: =fin_model!I63 -> #DIV/0! | D3: =fin_model!J63 -> #DIV/0! | E3: =fin_model!K63 -> #DIV/0! | F3: =fin_model!L63 -> #DIV/0! | G3: =fin_model!M63 -> #DIV/0! | H3: =fin_model!N63 -> #DIV/0!
B4: Capital expenditures (CAPEX) | C4: =fin_model!I66 -> #DIV/0! | D4: =fin_model!J66 -> #DIV/0! | E4: =fin_model!K66 -> #DIV/0! | F4: =fin_model!L66 -> #DIV/0! | G4: =fin_model!M66 -> #DIV/0! | H4: =fin_model!N66 -> #DIV/0!
B5: Net change in debt | C5: ='DCF_-_FCFE_341'!C5 -> #DIV/0! | D5: ='DCF_-_FCFE_341'!D5 -> #DIV/0! | E5: ='DCF_-_FCFE_341'!E5 -> #DIV/0! | F5: ='DCF_-_FCFE_341'!F5 -> #DIV/0! | G5: ='DCF_-_FCFE_341'!G5 -> #DIV/0! | H5: ='DCF_-_FCFE_341'!H5 -> #DIV/0!
B6: FCFE | C6: =SUM(C3:C5) -> #DIV/0! | D6: =SUM(D3:D5) -> #DIV/0! | E6: =SUM(E3:E5) -> #DIV/0! | F6: =SUM(F3:F5) -> #DIV/0! | G6: =SUM(G3:G5) -> #DIV/0! | H6: =SUM(H3:H5) -> #DIV/0!
B7: Terminal value (as a perpetuity) | I7: =D50 -> #DIV/0!
B8: Terminal value (from a multiple) | I8: =D54 -> #DIV/0!
B10: Share of year expected for CF or TV | C10: ='DCF_-_FCFF_timing'!C12 -> 1 | D10: ='DCF_-_FCFF_timing'!D12 -> 1 | E10: ='DCF_-_FCFF_timing'!E12 -> 1 | F10: ='DCF_-_FCFF_timing'!F12 -> 1 | G10: ='DCF_-_FCFF_timing'!G12 -> 1 | H10: ='DCF_-_FCFF_timing'!H12 -> 1 | I10: ='DCF_-_FCFF_timing'!I12 -> 1
B11: Expected FCFE or TV (as a perpetuity) | C11: =C6*C10 -> #DIV/0! | D11: =D6*D10 -> #DIV/0! | E11: =E6*E10 -> #DIV/0! | F11: =F6*F10 -> #DIV/0! | G11: =G6*G10 -> #DIV/0! | H11: =H6*H10 -> #DIV/0! | I11: =I7*I10 -> #DIV/0!
B12: Expected FCFE or TV (from a multiple) | C12: =C6*C10 -> #DIV/0! | D12: =D6*D10 -> #DIV/0! | E12: =E6*E10 -> #DIV/0! | F12: =F6*F10 -> #DIV/0! | G12: =G6*G10 -> #DIV/0! | H12: =H6*H10 -> #DIV/0! | I12: =I8*I10 -> #DIV/0!
B14: Terminal value (as a perpetuity)
B15: Period | C15: 1 | D15: 2 | E15: 3 | F15: 4 | G15: 5 | H15: 6 | I15: 6
B16: Years to discount | C16: =0.5*(1-YEARFRAC(C30,C31)) -> 0.5 | D16: =D15-YEARFRAC($C30,$C31)-0.5 -> 1.5 | E16: =E15-YEARFRAC($C30,$C31)-0.5 -> 2.5 | F16: =F15-YEARFRAC($C30,$C31)-0.5 -> 3.5 | G16: =G15-YEARFRAC($C30,$C31)-0.5 -> 4.5 | H16: =H15-YEARFRAC($C30,$C31)-0.5 -> 5.5 | I16: =I15-YEARFRAC($C30,$C31)-0.5 -> 5.5
B17: Present values with terminal value as a perpetuity | C17: =C11/(1+$C$27)^C16 -> #DIV/0! | D17: =D11/(1+$C$27)^D16 -> #DIV/0! | E17: =E11/(1+$C$27)^E16 -> #DIV/0! | F17: =F11/(1+$C$27)^F16 -> #DIV/0! | G17: =G11/(1+$C$27)^G16 -> #DIV/0! | H17: =H11/(1+$C$27)^H16 -> #DIV/0! | I17: =I11/(1+$C$27)^I16 -> #DIV/0!
B19: Terminal value (from a multiple)
B20: Period | C20: 1 | D20: 2 | E20: 3 | F20: 4 | G20: 5 | H20: 6 | I20: 6
B21: Years to discount | C21: =C16 -> 0.5 | D21: =D16 -> 1.5 | E21: =E16 -> 2.5 | F21: =F16 -> 3.5 | G21: =G16 -> 4.5 | H21: =H16 -> 5.5 | I21: =I20-YEARFRAC(C30,C31) -> 6
B22: Present values with terminal value from a multiple | C22: =C12/(1+$C$27)^C21 -> #DIV/0! | D22: =D12/(1+$C$27)^D21 -> #DIV/0! | E22: =E12/(1+$C$27)^E21 -> #DIV/0! | F22: =F12/(1+$C$27)^F21 -> #DIV/0! | G22: =G12/(1+$C$27)^G21 -> #DIV/0! | H22: =H12/(1+$C$27)^H21 -> #DIV/0! | I22: =I12/(1+$C$27)^I21 -> #DIV/0!
B24: Valuation Analysis
B25: Terminal growth rate | C25: ='DCF_-_FCFE_341'!C19 -> 0.01
B26: WACC | C26: ='DCF_-_FCFE_341'!C20 -> #DIV/0!
B27: Expected return of equity | C27: ='DCF_-_FCFE_341'!C21 -> 0.1242
B28: Terminal P/E | C28: 16
B30: Date of end of historical period | C30: ='DCF_-_FCFE_341'!C24 -> 0
B31: Valuation date | C31: ='DCF_-_FCFE_341'!C25 -> 0
J34: What-If Analysis of DCF-FCFE as a perpetuity
B35: Terminal value (as a perpetuity) | K35: Terminal Growth
B36: Estimated equity value (at valuation date) | C36: =SUM(C17:I17) -> #DIV/0! | H36: =C38 -> #DIV/0! | I36: -0.01 | J36: 0 | K36: 0.01 | L36: 0.015 | M36: 0.02
B37: Weighted average basic shares outstanding (in millions, end of historical period) | C37: ='DCF_-_FCFE_341'!C29 -> 0 | H37: 0.1221 | I37: #DIV/0! | J37: #DIV/0! | K37: #DIV/0! | L37: #DIV/0! | M37: #DIV/0!
B38: Estimated price per share (at valuation date) | C38: =C36/C37 -> #DIV/0! | H38: 0.1271 | I38: #DIV/0! | J38: #DIV/0! | K38: #DIV/0! | L38: #DIV/0! | M38: #DIV/0!
G39: Cost of Equity | H39: 0.1321 | I39: #DIV/0! | J39: #DIV/0! | K39: #DIV/0! | L39: #DIV/0! | M39: #DIV/0!
B40: Terminal value (from a multiple) | H40: 0.1371 | I40: #DIV/0! | J40: #DIV/0! | K40: #DIV/0! | L40: #DIV/0! | M40: #DIV/0!
B41: Estimated equity value (at valuation date) | C41: =SUM(C22:I22) -> #DIV/0! | H41: 0.1421 | I41: #DIV/0! | J41: #DIV/0! | K41: #DIV/0! | L41: #DIV/0! | M41: #DIV/0!
B42: Weighted average basic shares outstanding (in millions, end of historical period) | C42: =C37 -> 0
B43: Estimated price per share (at valuation date) | C43: =C41/C42 -> #DIV/0! | I43: Price at valuation | J43: ='DCF_-_FCFF_timing'!K49 -> 0
C46: FCFE | D46: =G6 -> #DIV/0! | J46: What-If Analysis of DCF-FCFE as a Multiple
C47: 1+g | D47: =1+C25 -> 1.01 | K47: Exit Multiple
C48: FCFE(N+1) | E48: =D46*D47 -> #DIV/0! | H48: =C43 -> #DIV/0! | I48: 13 | J48: 14.5 | K48: 16 | L48: 17.5 | M48: 19
C49: RE-g | E49: =C27-C25 -> 0.1142 | H49: 0.1222 | I49: #DIV/0! | J49: #DIV/0! | K49: #DIV/0! | L49: #DIV/0! | M49: #DIV/0!
C50: TV perp | D50: =E48/E49 -> #DIV/0! | H50: 0.1247 | I50: #DIV/0! | J50: #DIV/0! | K50: #DIV/0! | L50: #DIV/0! | M50: #DIV/0!
G51: Cost of Equity | H51: 0.1272 | I51: #DIV/0! | J51: #DIV/0! | K51: #DIV/0! | L51: #DIV/0! | M51: #DIV/0!
C52: NI | D52: =fin_model!N23 -> #DIV/0! | H52: 0.1297 | I52: #DIV/0! | J52: #DIV/0! | K52: #DIV/0! | L52: #DIV/0! | M52: #DIV/0!
C53: Exit mult | D53: =C28 -> 16 | H53: 0.1322 | I53: #DIV/0! | J53: #DIV/0! | K53: #DIV/0! | L53: #DIV/0! | M53: #DIV/0!
C54: TV mult | D54: =D52*D53 -> #DIV/0!
I55: Price at valuation | J55: =J43 -> 0

Sheet mkt_comps_raw_&_work
A4: Franklin Resources, Inc. (NYSE:BEN) > Quick Comparable Analysis > Financial Data
A7: Details
A8: Template: | B8: Capital IQ Default Comps
A9: Currency: | B9: US Dollar
A10: As-Of Date: | B10: 45657
A13: Company Comp Set
A14: Company Name | B14: Day Close Price Latest | C14: Shares Outstanding Latest | D14: Market Capitalization Latest | E14: LTM Net Debt | F14: LTM Total Pref. Equity | G14: LTM Minority Interest | H14: Total Enterprise Value Latest | I14: LTM Tangible Book Value/Share | J14: LTM Filing Date, Income Statement | K14: LTM Total Revenue | L14: LTM EBITDA | M14: LTM EBIT | N14: LTM Diluted EPS Excl. Extra Items
A15: T. Rowe Price Group, Inc. (NasdaqGS:TROW) | B15: 113.86 | C15: 222.2 | D15: 25295.1 | E15: -2809.3 | F15: - | G15: 966.8 | H15: 23452.6 | I15: 32.46 | J15: 45597 | K15: 6911.1 | L15: 2648.4 | M15: 2129.1 | N15: 9.13
A16: Invesco Ltd. (NYSE:IVZ) | B16: 17.48 | C16: 449.4 | D16: 7856.2 | E16: -154.6 | F16: 4010.5 | G16: 1152.3 | H16: 12864.4 | I16: -8.46 | J16: 45594 | K16: 5887.4 | L16: 1053 | M16: 871.1 | N16: -0.91
A17: Blackstone Inc. (NYSE:BX) | B17: 172.05 | C17: 767.9 | D17: 132116.4 | E17: 10343 | F17: - | G17: 12457.28 | H17: - | I17: 6.44 | J17: 45597 | K17: 11138.3 | L17: - | M17: - | N17: 2.9
A18: Northern Trust Corporation (NasdaqGS:NTRS) | B18: 102.74 | C18: 198.2 | D18: 20365 | E18: 7781.3 | F18: 884.9 | G18: - | H18: - | I18: 45.57 | J18: 45594 | K18: 7857.6 | L18: - | M18: - | N18: 8
A19: BlackRock, Inc. (NYSE:BLK) | B19: 1027.43 | C19: 154.9 | D19: 159127.3 | E19: -237 | F19: - | G19: 2446 | H19: 161336.3 | I19: 49.87 | J19: 45603 | K19: 19361 | L19: 7674 | M19: 7234 | N19: 40.52
A20: The Carlyle Group Inc. (NasdaqGS:CG) | B20: 50.52 | C20: 357.7 | D20: 18070.1 | E20: 7381.7 | F20: - | G20: 788.7 | H20: - | I20: 13.63 | J20: 45603 | K20: 4636.5 | L20: - | M20: - | N20: 0.33
A21: TPG Inc. (NasdaqGS:TPG) | B21: 63.41 | C21: 104.1 | D21: 6598.2 | E21: 385.4 | F21: - | G21: 2663.93 | H21: 9647.5 | I21: -2.69 | J21: 45600 | K21: 3406.8 | L21: 204.1 | M21: 83.2 | N21: -0.34
A22: The Charles Schwab Corporation (NYSE:SCHW) | B22: 73.93 | C22: 1830.6 | D22: 135333 | E22: -4167 | F22: 9191 | G22: - | H22: - | I22: 9.95 | J22: 45604 | K22: 18736 | L22: - | M22: - | N22: 2.56
A23: State Street Corporation (NYSE:STT) | B23: 98.28 | C23: 293.2 | D23: 28810.8 | E23: -68119 | F23: 2816 | G23: - | H23: - | I23: 47.63 | J23: 45596 | K23: 12548 | L23: - | M23: - | N23: 6.3
A24: Ares Management Corporation (NYSE:ARES) | B24: 179.02 | C24: 201.9 | D24: 36140.6 | E24: 12755.3 | F24: - | G24: 3803.46 | H24: 52699.3 | I24: -0.13 | J24: 45604 | K24: 3679.8 | L24: 1138.6 | M24: 982.2 | N24: 2.19
A27: Franklin Resources, Inc. (NYSE:BEN) | B27: 20.11 | C27: 523.7 | D27: 10531 | E27: 435.9 | F27: - | G27: 2056.7 | H27: 13023.6 | I27: 2.85 | J27: 45608 | K27: 8478 | L27: 1707.7 | M27: 1253 | N27: 0.85
A29: Summary Statistics | B29: Day Close Price Latest | C29: Shares Outstanding Latest | D29: Market Capitalization Latest | E29: LTM Net Debt | F29: LTM Total Pref. Equity | G29: LTM Minority Interest | H29: Total Enterprise Value Latest | I29: LTM Tangible Book Value/Share | J29: LTM Filing Date, Income Statement | K29: LTM Total Revenue | L29: LTM EBITDA | M29: LTM EBIT | N29: LTM Diluted EPS Excl. Extra Items
A30: High | B30: 1027.43 | C30: 1830.6 | D30: 159127.3 | E30: 12755.3 | F30: 9191 | G30: 12457.28 | H30: 161336.3 | I30: 49.87 | J30: - | K30: 19361 | L30: 7674 | M30: 7234 | N30: 40.52
A31: Low | B31: 17.48 | C31: 104.1 | D31: 6598.2 | E31: -68119 | F31: 884.9 | G31: 788.7 | H31: 9647.5 | I31: -8.46 | J31: - | K31: 3406.8 | L31: 204.1 | M31: 83.2 | N31: -0.91
A32: Mean | B32: 189.87 | C32: 458 | D32: 56971.3 | E32: -3684 | F32: 4225.6 | G32: 3468.35 | H32: 52000 | I32: 19.43 | J32: - | K32: 9416.2 | L32: 2543.6 | M32: 2259.9 | N32: 7.07
A33: Median | B33: 100.51 | C33: 257.7 | D33: 27053 | E33: 115.4 | F33: 3413.25 | G33: 2446 | H33: 23452.6 | I33: 11.79 | J33: - | K33: 7384.4 | L33: 1138.6 | M33: 982.2 | N33: 2.73

Sheet mkt_comps_summary
A1: Company Name | B1: Day Close Price Latest | C1: Shares Outstanding Latest | D1: Market Capitalization Latest | E1: LTM Net Debt | F1: LTM Total Pref. Equity | G1: LTM Minority Interest | H1: Total Enterprise Value Latest | I1: LTM Tangible Book Value/Share | J1: LTM Filing Date, Income Statement | K1: LTM Total Revenue | L1: LTM EBITDA | M1: LTM EBIT | N1: LTM Diluted EPS Excl. Extra Items | O1: Denominator for the other multiple based on enterprise value | P1: Denominator for the other multiple based on equity value | Q1: Denominator for the other multiple based on equity value per share (may be same as previous column or may need to divide previous column by number of shares) | R1: LTM unlevered | S1: LTM levered | T1: 2023 Unlevered | U1: 2023 Levered
R2: 823.6 | S2: 747.3 | T2: 779.9 | U2: 702.5
R5: 3.5 | S5: 2.3 | T5: 51.8 | U5: 49.2
R8: -34.2 | S8: -54.2 | T8: 109.5 | U8: 100.5
O12: =T12 -> 0 | P12: =U12 -> 0
O13: =T13 -> 0 | P13: =U13 -> 0
R14: 967.7 | S14: 858.3 | T14: 1103.18 | U14: 986.7375
A15: *Fill in peer firms above the black cells and firm being valued below the black cells
A16: **Only fill in data for peers that are included in the peer group. If you decide to drop any firms from the original peer group, do not include their data above. Just leave the row blank. If you add any firms to the original peer group, then include them in the yellow section above the black cells. Do not include more than 10 peers.
A19: Multiple | B19: 35th percentile peer multiple | C19: 65th percentile peer multiple | J19: =(fin_model!C5*C14)/L14 -> #DIV/0! | O19: (unlevered) | P19: (levered)
A20: EV/EBITDA | B20: {=TRANSPOSE(B44:H44)} -> #DIV/0! | C20: {=TRANSPOSE(B45:H45)} -> #DIV/0! | E20: Peer stats
A21: EV/EBIT | B21: #DIV/0! | C21: #DIV/0! | E21: Company | F21: EV/EBITDA | G21: EV/EBIT | H21: EV/Sales | I21: P/E | J21: P/B | K21: EV/FCFF | L21: P/FCFE
A22: EV/sales | B22: #DIV/0! | C22: #DIV/0! | E22: =A2 -> 0 | F22: =H2/L2 -> #DIV/0! | G22: =H2/M2 -> #DIV/0! | H22: =H2/K2 -> #DIV/0! | I22: =B2/N2 -> #DIV/0! | J22: =B2/I2 -> #DIV/0! | K22: =H2/O2 -> #DIV/0! | L22: =B2/P2 -> #DIV/0!
A23: P/E | B23: #DIV/0! | C23: #DIV/0! | E23: =A3 -> 0 | F23: =H3/L3 -> #DIV/0! | G23: =H3/M3 -> #DIV/0! | H23: =H3/K3 -> #DIV/0!
A24: P/B | B24: #DIV/0! | C24: #DIV/0!
A25: EV/FCFF | B25: #DIV/0! | C25: #DIV/0! | E25: =A5 -> 0 | I25: =B5/N5 -> #DIV/0! | J25: =B5/I5 -> #DIV/0! | L25: =B5/P5 -> #DIV/0! | N25: Check for negative values
A26: P/FCFE per share | B26: #DIV/0! | C26: #DIV/0! | N26: =MIN(F22:L31) -> #DIV/0!
A27: * Fill in the cells in this table with the values of each multiple, not estimated prices
E28: =A8 -> 0 | F28: =H8/L8 -> #DIV/0! | G28: =H8/M8 -> #DIV/0! | H28: =H8/K8 -> #DIV/0! | K28: =H8/O8 -> #DIV/0! | L28: =B8/P8 -> #DIV/0!
A30: Multiple | B30: Low (value) - estimated price, which is the estimated price of your firm based on the 35th percentile peer multiple | C30: High (value) - estimated price, which is the estimated price of your firm based on the 65th percentile peer multiple | E30: =A10 -> 0 | I30: =B10/N10 -> #DIV/0! | J30: =B10/I10 -> #DIV/0!
A31: EV/EBITDA | B31: {=TRANSPOSE(B60:H60)} -> #DIV/0! | C31: {=TRANSPOSE(B61:H61)} -> #DIV/0! | E31: =A11 -> 0 | F31: =H11/L11 -> #DIV/0! | G31: =H11/M11 -> #DIV/0! | H31: =H11/K11 -> #DIV/0! | I31: =B11/N11 -> #DIV/0!
A32: EV/EBIT | B32: #DIV/0! | C32: #DIV/0!
A33: EV/sales | B33: #DIV/0! | C33: #DIV/0!
A34: P/E | B34: #DIV/0! | C34: #DIV/0!
A35: P/B | B35: #DIV/0! | C35: #DIV/0! | N35: Error if less than 0
A36: EV/FCFF | B36: #DIV/0! | C36: #DIV/0! | N36: =MIN(F22:L24) -> #DIV/0!
A37: P/FCFE per share | B37: #DIV/0! | C37: #DIV/0!
A38: * Fill in the cells in this table with estimated prices
A43: Summary statistics | B43: EV/EBITDA | C43: EV/EBIT | D43: EV/sales | E43: P/E | F43: P/B | G43: EV/FCFF | H43: P/FCFE
A44: 35th percentile | B44: =_xlfn.PERCENTILE.INC(F22:F31,0.35) -> #DIV/0! | C44: =_xlfn.PERCENTILE.INC(G22:G31,0.35) -> #DIV/0! | D44: =_xlfn.PERCENTILE.INC(H22:H31,0.35) -> #DIV/0! | E44: =_xlfn.PERCENTILE.INC(I22:I31,0.35) -> #DIV/0! | F44: =_xlfn.PERCENTILE.INC(J22:J31,0.35) -> #DIV/0! | G44: =_xlfn.PERCENTILE.INC(K22:K31,0.35) -> #DIV/0! | H44: =_xlfn.PERCENTILE.INC(L22:L31,0.35) -> #DIV/0!
A45: 65th percentile | B45: =_xlfn.PERCENTILE.INC(F22:F31,0.65) -> #DIV/0! | C45: =_xlfn.PERCENTILE.INC(G22:G31,0.65) -> #DIV/0! | D45: =_xlfn.PERCENTILE.INC(H22:H31,0.65) -> #DIV/0! | E45: =_xlfn.PERCENTILE.INC(I22:I31,0.65) -> #DIV/0! | F45: =_xlfn.PERCENTILE.INC(J22:J31,0.65) -> #DIV/0! | G45: =_xlfn.PERCENTILE.INC(K22:K31,0.65) -> #DIV/0! | H45: =_xlfn.PERCENTILE.INC(L22:L31,0.65) -> #DIV/0!
A49: Enterprise Value | B49: EV/EBITDA | C49: EV/EBIT | D49: EV/sales | E49: P/E | F49: P/B | G49: EV/FCFF | H49: P/FCFE
A50: 35th percentile | B50: =B44*$L$14 -> #DIV/0! | C50: =C44*$M$14 -> #DIV/0! | D50: =D44*$K$14 -> #DIV/0! | G50: =G44*O14 -> #DIV/0!
A51: 65th percentile | B51: =B45*$L$14 -> #DIV/0! | C51: =C45*$M$14 -> #DIV/0! | D51: =D45*$K$14 -> #DIV/0! | G51: =G45*O14 -> #DIV/0!
A54: Equity Value | B54: EV/EBITDA | C54: EV/EBIT | D54: EV/sales | E54: P/E | F54: P/B | G54: EV/FCFF | H54: P/FCFE
A55: 35th percentile | B55: =B50-SUM($E$14:$G$14) -> #DIV/0! | C55: =C50-SUM($E$14:$G$14) -> #DIV/0! | D55: =D50-SUM($E$14:$G$14) -> #DIV/0! | G55: =G50-SUM($E$14:$G$14) -> #DIV/0!
A56: 65th percentile | B56: =B51-SUM($E$14:$G$14) -> #DIV/0! | C56: =C51-SUM($E$14:$G$14) -> #DIV/0! | D56: =D51-SUM($E$14:$G$14) -> #DIV/0! | G56: =G51-SUM($E$14:$G$14) -> #DIV/0!
A59: Share Price | B59: EV/EBITDA | C59: EV/EBIT | D59: EV/sales | E59: P/E | F59: P/B | G59: EV/FCFF | H59: P/FCFE
A60: 35th percentile | B60: =B55/$C$14 -> #DIV/0! | C60: =C55/$C$14 -> #DIV/0! | D60: =D55/$C$14 -> #DIV/0! | E60: =E44*N14 -> #DIV/0! | F60: =F44*$I$14 -> #DIV/0! | G60: =G55/$C$14 -> #DIV/0! | H60: =H44*Q14 -> #DIV/0!
A61: 65th percentile | B61: =B56/$C$14 -> #DIV/0! | C61: =C56/$C$14 -> #DIV/0! | D61: =D56/$C$14 -> #DIV/0! | E61: =E45*N14 -> #DIV/0! | F61: =F45*$I$14 -> #DIV/0! | G61: =G56/$C$14 -> #DIV/0! | H61: =H45*Q14 -> #DIV/0!
C63: Low Val | D63: Low lab | E63: high val | F63: high lab
C64: 0.35 | E64: 0.65
B65: {=TRANSPOSE(B59:H59)} -> EV/EBITDA | C65: {=TRANSPOSE(B60:H60)} -> #DIV/0! | D65: =C65 -> #DIV/0! | E65: {=TRANSPOSE(B61:H61)} -> #DIV/0! | F65: =E65 -> #DIV/0!
B66: EV/EBIT | C66: #DIV/0! | D66: =C66 -> #DIV/0! | E66: #DIV/0! | F66: =E66 -> #DIV/0!
B67: EV/sales | C67: #DIV/0! | D67: =C67 -> #DIV/0! | E67: #DIV/0! | F67: =E67 -> #DIV/0!
B68: P/E | C68: #DIV/0! | D68: =C68 -> #DIV/0! | E68: #DIV/0! | F68: =E68 -> #DIV/0!
B69: P/B | C69: #DIV/0! | D69: =C69 -> #DIV/0! | E69: #DIV/0! | F69: =E69 -> #DIV/0!
B70: EV/FCFF | C70: #DIV/0! | D70: =C70 -> #DIV/0! | E70: #DIV/0! | F70: =E70 -> #DIV/0!
B71: P/FCFE | C71: #DIV/0! | D71: =C71 -> #DIV/0! | E71: #DIV/0! | F71: =E71 -> #DIV/0!

Sheet Residual_inc
B1: Date of end of historical period | C1: ='DCF_-_FCFE_timing'!C30 -> 0
B2: Valuation date | C2: ='DCF_-_FCFE_timing'!C31 -> 0
B3: Cost of equity | C3: =WACC!B36 -> 0.1242
B4: Number of shares (at end of historical period) | C4: =fin_model!H54 -> 0
B5: Terminal growth | C5: ='DCF_-_FCFE_341'!C19 -> 0.01
B6: Persisitence factor (ω) | C6: 0.5 | E6: between 0 and 1, with 1 being high persistence
B9: Approach 1: forecast RIs & assume constant growth for subsequent RIs
C10: BVE0 | D10: RI1 | E10: RI2 | F10: RI3 | G10: RI4 | H10: RI5 | I10: TV
B11: Discount periods | C11: 0 | D11: 1 | E11: 2 | F11: 3 | G11: 4 | H11: 5 | I11: 5
B12: Amount | C12: =fin_model!H51 -> 0 | D12: =D39 -> #DIV/0! | E12: =E39 -> #DIV/0! | F12: =F39 -> #DIV/0! | G12: =G39 -> #DIV/0! | H12: =H39 -> #DIV/0! | I12: =J44 -> #DIV/0!
B13: Present value of amount | C13: =C12/(1+$C$3)^C11 -> 0 | D13: =D12/(1+$C$3)^D11 -> #DIV/0! | E13: =E12/(1+$C$3)^E11 -> #DIV/0! | F13: =F12/(1+$C$3)^F11 -> #DIV/0! | G13: =G12/(1+$C$3)^G11 -> #DIV/0! | H13: =H12/(1+$C$3)^H11 -> #DIV/0! | I13: =I12/(1+$C$3)^I11 -> #DIV/0!
B14: Market value of equity as of end of historical period | C14: =SUM(C13:I13) -> #DIV/0!
B15: Estimated share price as of end of historical period | C15: =C14/C4 -> #DIV/0!
B16: Estimated share price at valuation date | C16: =C15*(1+C3)^E29 -> #DIV/0!
B19: Approach 2: forecast RIs & assume persistent factor for subsequent RIs
C20: BVE0 | D20: RI1 | E20: RI2 | F20: RI3 | G20: RI4 | H20: RI5 | I20: Val Cont RI | K20: Persistence (ω) | L20: =C26 -> #DIV/0!
B21: Discount periods | C21: 0 | D21: 1 | E21: 2 | F21: 3 | G21: 4 | H21: 5 | I21: 5 | K21: 0 | L21: #DIV/0!
B22: Amount | C22: =fin_model!H51 -> 0 | D22: =D39 -> #DIV/0! | E22: =E39 -> #DIV/0! | F22: =F39 -> #DIV/0! | G22: =G39 -> #DIV/0! | H22: =H39 -> #DIV/0! | I22: =H51 -> #DIV/0! | K22: 0.1 | L22: #DIV/0!
B23: Present value of amount | C23: =C22/(1+$C3)^C21 -> 0 | D23: =D22/(1+$C3)^D21 -> #DIV/0! | E23: =E22/(1+$C3)^E21 -> #DIV/0! | F23: =F22/(1+$C3)^F21 -> #DIV/0! | G23: =G22/(1+$C3)^G21 -> #DIV/0! | H23: =H22/(1+$C3)^H21 -> #DIV/0! | I23: =I22/(1+$C3)^I21 -> #DIV/0! | K23: =K22+0.1 -> 0.2 | L23: #DIV/0!
B24: Market value of equity as of end of historical period | C24: =SUM(C23:I23) -> #DIV/0! | K24: =K23+0.1 -> 0.3 | L24: #DIV/0!
B25: Estimated share price as of end of historical period | C25: =C24/C4 -> #DIV/0! | K25: =K24+0.1 -> 0.4 | L25: #DIV/0!
B26: Estimated share price at valuation date | C26: =C25*(1+C3)^E29 -> #DIV/0! | K26: =K25+0.1 -> 0.5 | L26: #DIV/0!
K27: =K26+0.1 -> 0.6 | L27: #DIV/0!
E28: YearFrac | K28: =K27+0.1 -> 0.7 | L28: #DIV/0!
E29: =YEARFRAC(C1,C2) -> 0 | K29: =K28+0.1 -> 0.8 | L29: #DIV/0!
K30: =K29+0.1 -> 0.9 | L30: #DIV/0!
K31: =K30+0.1 -> 1 | L31: #DIV/0!
K32: 1 | L32: =L31 -> #DIV/0!
B34: Period | D34: 1 | E34: 2 | F34: 3 | G34: 4 | H34: 5 | I34: 6
B35: Net income | D35: =fin_model!I23 -> #DIV/0! | E35: =fin_model!J23 -> #DIV/0! | F35: =fin_model!K23 -> #DIV/0! | G35: =fin_model!L23 -> #DIV/0! | H35: =fin_model!M23 -> #DIV/0! | I35: =fin_model!N23 -> #DIV/0!
B36: Equity | D36: =fin_model!I51 -> #DIV/0! | E36: =fin_model!J51 -> #DIV/0! | F36: =fin_model!K51 -> #DIV/0! | G36: =fin_model!L51 -> #DIV/0! | H36: =fin_model!M51 -> #DIV/0! | I36: =fin_model!N51 -> #DIV/0!
B37: RE | D37: =$C3 -> 0.1242 | E37: =$C3 -> 0.1242 | F37: =$C3 -> 0.1242 | G37: =$C3 -> 0.1242 | H37: =$C3 -> 0.1242 | I37: =$C3 -> 0.1242
B38: Equity charge | D38: =D36*D37 -> #DIV/0! | E38: =E36*E37 -> #DIV/0! | F38: =F36*F37 -> #DIV/0! | G38: =G36*G37 -> #DIV/0! | H38: =H36*H37 -> #DIV/0! | I38: =I36*I37 -> #DIV/0!
B39: Residual Income | D39: =D35-D38 -> #DIV/0! | E39: =E35-E38 -> #DIV/0! | F39: =F35-F38 -> #DIV/0! | G39: =G35-G38 -> #DIV/0! | H39: =H35-H38 -> #DIV/0! | I39: =I35-I38 -> #DIV/0!
B41: "TV3" = RI4 / (RE - g)
B42: RI4 | I42: =I39 -> #DIV/0!
B43: RE - g | I43: =C3-C5 -> 0.1142
B44: TV3 | J44: =I42/I43 -> #DIV/0!
B47: {RIN+1}/ {(1+RE – ω)
B48: RI(N+1) = RI4 | H48: =I42 -> #DIV/0!
B49: Omega = persistence factor | H49: =C6 -> 0.5
B50: (1 + RE - omega) | H50: =1+C3-H49 -> 0.6242
B51: "TV3" | H51: =H48/H50 -> #DIV/0!

Sheet final_table
J2: Weights between DCF, Comps, and RI | K2: Weights within valuation methods
E3: Low Val | F3: Low Label | G3: High Val | H3: High Label | Q3: Mid value
C4: ='DCF_-_FCFF_timing'!C41 -> #DIV/0! | D4: DCF-FCFF perp | E4: =C4*(B10) -> #DIV/0! | F4: =E4 -> #DIV/0! | G4: =C4*C10 -> #DIV/0! | H4: =G4 -> #DIV/0! | J4: 0.6 | K4: 0.25 | L4: =K4*E4 -> #DIV/0! | M4: =G4*K4 -> #DIV/0! | Q4: =C4*K4*J4 -> #DIV/0!
C5: ='DCF_-_FCFF_timing'!C48 -> #DIV/0! | D5: DCF-FCFF mult | E5: =C5*B10 -> #DIV/0! | F5: =E5 -> #DIV/0! | G5: =C5*C10 -> #DIV/0! | H5: =G5 -> #DIV/0! | J5: =J4 -> 0.6 | K5: 0 | L5: =K5*E5 -> #DIV/0! | M5: =G5*K5 -> #DIV/0! | Q5: =C5*K5*J5 -> #DIV/0!
C6: ='DCF_-_FCFE_timing'!C38 -> #DIV/0! | D6: DCF-FCFE perp | E6: =C6*B10 -> #DIV/0! | F6: =E6 -> #DIV/0! | G6: =C6*C10 -> #DIV/0! | H6: =G6 -> #DIV/0! | J6: =J5 -> 0.6 | K6: 0.75 | L6: =K6*E6 -> #DIV/0! | M6: =G6*K6 -> #DIV/0! | Q6: =C6*K6*J6 -> #DIV/0!
C7: ='DCF_-_FCFE_timing'!C43 -> #DIV/0! | D7: DCF-FCFE mult | E7: =C7*B10 -> #DIV/0! | F7: =E7 -> #DIV/0! | G7: =C7*C10 -> #DIV/0! | H7: =G7 -> #DIV/0! | J7: =J6 -> 0.6 | K7: 0 | L7: =K7*E7 -> #DIV/0! | M7: =G7*K7 -> #DIV/0! | N7: =SUM(L4:L7)*J4 -> #DIV/0! | O7: =SUM(M4:M7)*J4 -> #DIV/0! | Q7: =C7*K7*J7 -> #DIV/0!
D8: EV/EBITDA | E8: =mkt_comps_summary!C65 -> #DIV/0! | F8: =E8 -> #DIV/0! | G8: =mkt_comps_summary!E65 -> #DIV/0! | H8: =G8 -> #DIV/0! | J8: 0 | K8: 0.14285714 | L8: =IFERROR(K8*E8,"No Values") -> No Values | M8: =IFERROR(G8*K8,"No Values") -> No Values | Q8: =C8*K8*J8 -> 0
B9: Confidence int | D9: EV/EBIT | E9: =mkt_comps_summary!C66 -> #DIV/0! | F9: =E9 -> #DIV/0! | G9: =mkt_comps_summary!E66 -> #DIV/0! | H9: =G9 -> #DIV/0! | J9: =J8 -> 0 | K9: 0.14285714 | L9: =IFERROR(K9*E9,"No Values") -> No Values | M9: =IFERROR(G9*K9,"No Values") -> No Values | Q9: =C9*K9*J9 -> 0
B10: 0.9 | C10: 1.1 | D10: EV/Sales | E10: =mkt_comps_summary!C67 -> #DIV/0! | F10: =E10 -> #DIV/0! | G10: =mkt_comps_summary!E67 -> #DIV/0! | H10: =G10 -> #DIV/0! | J10: =J9 -> 0 | K10: 0.14285714 | L10: =IFERROR(K10*E10,"No Values") -> No Values | M10: =IFERROR(G10*K10,"No Values") -> No Values | Q10: =C10*K10*J10 -> 0
D11: P/E | E11: =mkt_comps_summary!C68 -> #DIV/0! | F11: =E11 -> #DIV/0! | G11: =mkt_comps_summary!E68 -> #DIV/0! | H11: =G11 -> #DIV/0! | J11: =J10 -> 0 | K11: 0.14285714 | L11: =IFERROR(K11*E11,"No Values") -> No Values | M11: =IFERROR(G11*K11,"No Values") -> No Values | Q11: =C11*K11*J11 -> 0
D12: P/B | E12: =mkt_comps_summary!F60 -> #DIV/0! | F12: =E12 -> #DIV/0! | G12: =mkt_comps_summary!F61 -> #DIV/0! | H12: =G12 -> #DIV/0! | J12: =J11 -> 0 | K12: 0.14285714 | L12: =IFERROR(K12*E12,"No Values") -> No Values | M12: =IFERROR(G12*K12,"No Values") -> No Values | Q12: =C12*K12*J12 -> 0
D13: EV/FCFF | E13: =mkt_comps_summary!C70 -> #DIV/0! | F13: =E13 -> #DIV/0! | G13: =mkt_comps_summary!E70 -> #DIV/0! | H13: =G13 -> #DIV/0! | J13: =J12 -> 0 | K13: 0.14285714 | L13: =IFERROR(K13*E13,"No Values") -> No Values | M13: =IFERROR(G13*K13,"No Values") -> No Values | Q13: =C13*K13*J13 -> 0
D14: P/FCFE | E14: =mkt_comps_summary!C71 -> #DIV/0! | F14: =E14 -> #DIV/0! | G14: =mkt_comps_summary!E71 -> #DIV/0! | H14: =G14 -> #DIV/0! | J14: =J13 -> 0 | K14: 0.14285714 | L14: =IFERROR(K14*E14,"No Values") -> No Values | M14: =IFERROR(G14*K14,"No Values") -> No Values | N14: =IFERROR(SUM(L8:L14)*J8,"0") -> 0 | O14: =IFERROR(SUM(M8:M14)*J8,"0") -> 0 | Q14: =C14*K14*J14 -> 0 | S14: Price
D15: Residual Income | E15: =Residual_inc!C26*B10 -> #DIV/0! | F15: =E15 -> #DIV/0! | G15: =Residual_inc!C26*C10 -> #DIV/0! | H15: =G15 -> #DIV/0! | J15: 0.4 | K15: 1 | L15: =K15*E15 -> #DIV/0! | M15: =G15*K15 -> #DIV/0! | N15: =L15*J15 -> #DIV/0! | O15: =M15*J15 -> #DIV/0! | Q15: =K15*J15*AVERAGE(F15:G15) -> #DIV/0! | R15: Bear Val. | S15: =N16 -> #DIV/0!
N16: =SUM(N4:N15) -> #DIV/0! | O16: =SUM(O4:O15) -> #DIV/0! | Q16: =SUM(Q4:Q15) -> #DIV/0! | R16: Price of BEN 1/14/25 | S16: 19.41
I17: Sum of weights | J17: =SUM(J4,J8,J15) -> 1 | K17: =SUM(K4:K15)/3 -> 1 | R17: Base Val. | S17: =Q16 -> #DIV/0!
N18: Recommendation | R18: Bull Val. | S18: =O16 -> #DIV/0!
L19: price as of valuation | M19: =fin_model!C5 -> 0 | N19: =IF(M19>O16,"sell",IF(M19>N16,"Hold","Buy")) -> #DIV/0!
L21: ="The price today should be between " & "$" & ROUND(S15,2) & " and " & "$" &ROUND(S18,2) -> #DIV/0!
U24: =J4*K4 -> 0.15
U25: =J6*K6 -> 0.45
U26: =J15 -> 0.4

Sheet Sheet2
